Workbook

Sheet Work Card Inquiry
A1: GAES WO# | B1: GAES Source Card# | C1: CUST. CARD | D1: PROJECT | E1: ORDER TYPE | F1: DESCRIPTION | G1: CORRECTIVE ACTION
A2: 20091-0001 | B2: - | C2: WY | D2: CN-RGA-1 | E2: ROUTINE | F2: WEEKLY CHECK REF TASK WY | G2: COMPLETED. TLB# TL2311637 ITEM "C".
A3: 20092-0001 | B3: - | C3: 12-004-00-01 | D3: CN-RGA-1 | E3: ROUTINE | F3: CHANGE ENGINE 1 INTEGRATED DRIVE GENERATOR OIL. REF TASK 12-004-00-01 | G3: COMPLETED.
A4: 20092-0002 | B4: - | C4: 12-004-00-02 | D4: CN-RGA-1 | E4: ROUTINE | F4: CHANGE ENGINE 2 INTEGRATED DRIVE GENERATOR OIL. REF TASK 12-004-00-02 | G4: COMPLETED.
A5: 20092-0003 | B5: - | C5: 12-004-00-03 | D5: CN-RGA-1 | E5: ROUTINE | F5: CHANGE ENGINE 3 INTEGRATED DRIVE GENERATOR OIL. REF TASK 12-004-00-03 | G5: COMPLETED.
A6: 20092-0004 | B6: - | C6: 12-004-00-04 | D6: CN-RGA-1 | E6: ROUTINE | F6: CHANGE ENGINE 4 INTEGRATED DRIVE GENERATOR OIL. REF TASK 12-004-00-04 | G6: COMPLETED.
A7: 20092-0005 | B7: - | C7: 12-078-00-04 | D7: CN-RGA-1 | E7: ROUTINE | F7: FUNCTIONALLY CHECK THE TIRE PRESSURE INDICATION SYSTEM, IF INSTALLED. REF TASK 12-078-00-04 | G7: COMPLETED.
A8: 20092-0006 | B8: - | C8: 12-080-00 | D8: CN-RGA-1 | E8: ROUTINE | F8: FUNCTIONAL CHECK OF THE PARKING BRAKE ACCUMULATOR CHARGE PRESSURE. REF TASK 12-080-00 | G8: COMPLETED.
A9: 20092-0007 | B9: - | C9: 12-082-00-01 | D9: CN-RGA-1 | E9: ROUTINE | F9: SERVICE THE BRAKE SURGE ACCUMULATOR PRECHARGE (RIGHT BODY LANDING GEAR WELL). REF TASK 12-082-00-01 | G9: COMPLETED.
A10: 20092-0008 | B10: - | C10: 12-082-00-02 | D10: CN-RGA-1 | E10: ROUTINE | F10: SERVICE THE BRAKE SURGE ACCUMULATOR PRECHARGE (LEFT WING REAR SPAR TO LANDING GEAR SUPPORT BEAM). REF TASK 12-082-00-02 | G10: COMPLETED.
A11: 20092-0009 | B11: - | C11: 12-082-00-03 | D11: CN-RGA-1 | E11: ROUTINE | F11: SERVICE THE BRAKE SURGE ACCUMULATOR PRECHARGE (RIGHT REAR SPAR TO LANDING GEAR SUPPORT BEAM). REF TASK 12-082-00-03 | G11: COMPLETED.
A12: 20092-0010 | B12: - | C12: 12-084-00-01 | D12: CN-RGA-1 | E12: ROUTINE | F12: LUBRICATE LEFT BODY LANDING GEAR TRUCK BEAM PIVOT BOLT. REF TASK 12-084-00-01 | G12: COMPLETED.
... A638: 20110-0010 | B638: - | C638: GAES PROCEDURE | D638: CN-RGA-1 | E638: NONROUTINE | F638: PERFORM REMOVAL/INSTALLATION OF ACCESS PANELS FOR ZONE 800 AS PER PANEL CLEARANCE SHEETS GAES-148-AMO-REV00-JUL2023 | G638: COMPLETED.
A639: 20110-0011 | B639: 20097-0022 | D639: CN-RGA-1 | E639: NONROUTINE | F639: ENG 4- *BLEED PRV ENG 4* STATUS MESSAGE. PERFORM CORRECTIVE ACTION | G639: COMPLETED.
A640: 20110-0012 | B640: 20099-0034 | D640: CN-RGA-1 | E640: NONROUTINE | F640: CARRY OUT REMOVAL AND INSTALLATION OF PAX SEATS FROM STA 1000 TO STA 1480 (19ABC HJK TO 39 ABC HJK) BOTH LH AND RH SIDE TO ACCESS THE FLOOR PANEL. | G640: COMPLETED.
A641: 20110-0013 | B641: 20092-0083 | D641: CN-RGA-1 | E641: NONROUTINE | F641: ENG 3- INLET COWL INNER ACOUSTIC PANEL BULGIE ON 6'0 CLOCK POSITION . PERFORM CORRECTIVE ACTION | G641: COMPLETED.
A642: 20110-0014 | B642: 20099-0054 | D642: CN-RGA-1 | E642: NONROUTINE | F642: PERFORM CLEANING OF THE FAN COWLS,T/RS AND CORE COWLS INNER SURFACE FOR ALL ENGINES. | G642: COMPLETED.
A643: 20110-0015 | B643: 20099-0032 | D643: CN-RGA-1 | E643: NONROUTINE | F643: IN LAVATORY FC2 THE WASTE COMPARTMENT FLAPPER IS WEAK. | G643: COMPLETED.
A644: 20110-0016 | B644: 20099-0032 | D644: CN-RGA-1 | E644: NONROUTINE | F644: IN LAVATORY BS2 THE WASTE COMPARTMENT DOOR SCREWS QTY 3 ARE MISSING. | G644: COMPLETED.
A645: 20110-0017 | B645: 20099-0032 | D645: CN-RGA-1 | E645: NONROUTINE | F645: IN LAVATORY FC2 THE WASTE CONTAINER IS DIRTY. | G645: COMPLETED.
A646: 20110-0018 | B646: 20092-0079 | D646: CN-RGA-1 | E646: NONROUTINE | F646: RH WING LE UPPER FIXED PANEL FOUND PUNCTURE BETWEEN OLES 1639.00 AND WBL 1241.00. PLS RECTIFY. | G646: COMPLETED.
A647: 20110-0019 | B647: 20092-0030 | D647: CN-RGA-1 | E647: NONROUTINE | F647: MAIN 3 AFT OVRD/JETTISON PUMP "LOW PRESSURE'' LIGHT IS NOT ILLUMINATING. PERFORM CORRECTIVE ACTION | G647: COMPLETED.
A648: 20110-0020 | B648: 20092-0049 | D648: CN-RGA-1 | E648: NONROUTINE | F648: MASTER DIM AND TEST MODULE OPC FAILED: INDICATOR LIGHTS DOESN'T GO OFF WHEN SWITCH PLACED FROM "TEST" TO "BRIGHT" POSITION. PERFORM CORRECTIVE ACTION | G648: COMPLETED.
A649: 20110-0021 | B649: 20092-0026 | D649: CN-RGA-1 | E649: NONROUTINE | F649: FOUND INTERMITTENT PRESENT LEG FAULT, MMSG 26040: ''ENGINE BOTTLE RIGHT-A LOW PRESSURE'' AND ''BTL LOW R ENG A'' STATUS MSG. PERFORM CORRECTIVE ACTION | G649: COMPLETED.
A650: 20110-0022 | B650: 20092-0084 | D650: CN-RGA-1 | E650: NONROUTINE | F650: PERFORM REPAIR OF THE ENG#4 RH T/R FILLER . | G650: COMPLETED.
... A722: 20110-0094 | B722: 20110-0002 | D722: CN-RGA-1 | E722: NONROUTINE | F722: ENG 4 -DURING ENGINE START FOUND *BLD 4 OVHT/PRV* ADVISORY MESSAGE APPEAR. PERFORM CORRECTIVE ACTION | G722: TO AVOID DELAY AIRCARFT DISPATCHED I.A.W MEL 36-11-08B AND MEL 78-31-01 REV.01 CAT "C" ENGINE NO. 4 THRUST REVERSER DEACTIVATED. REFER TO TLB# TL2311637 ITEM "B".
A723: 20114-0001 | B723: - | C723: CWR-001 | D723: CN-RGA-1 | E723: CWR | F723: PERFORM AICRAFT EXTERNAL WASH | G723: COMPLETED.
A724: 20116-0001 | B724: - | D724: AP-BNU-1 | E724: GENERIC | F724: TASK CARD CREATED TO LINK MATERIALS ORDERED FOR PHASE 1, BUT POSTPONNED TO PHASE 2 | G724: CANCELLED. ALL RQ TRASNFERRED TO NRC RQ
A725: 20116-0002 | B725: - | D725: AP-BNU-1 | E725: GENERIC | F725: TASK CARD CREATED TO ORDER PAINT MATERIALS AND TRACKING ONLY. REPAINT THE AIRCRAFT PER EOD-B747-51-21-0001 1/4 & 2/4 INSTRUCTIONS. PERFORM A POST PAINT CONTROL AND SURFACE BALANCING PER EOD-B747-51-21-0001 3/4 INSTRUCTIONS. REF TASK AMES/MP/10-007 RT717-BM-2401-1 | G725: CANCELLED. ALL REQUISITON TRANSFERRED TO 20148-0001
A726: 20117-0001 | B726: - | C726: 27-062-06 | D726: CN-RGA-1 | E726: ROUTINE | F726: PERFORM AN OPERATIONAL CHECK OF THE AUTO SPEED BRAKE ACTUATION SYSTEM AND THE CONTROL STAND CAM MECHANISM. REF TASK 27-062-06 | G726: REFER TO RC# 20097-0016
A727: 20117-0002 | B727: - | C727: 28-022-04 | D727: CN-RGA-1 | E727: ROUTINE | F727: OPERATIONALLY CHECK THE ENGINE FUEL SUCTION FEED SYSTEM (REF FAA AD 2013-13-11) REF TASK 28-022-04 | G727: REFER TO RC# 20097-002
A728: 20121-0001 | B728: - | C728: 27-450-00-01 | D728: VQ-BXJ-1 | E728: ROUTINE | F728: INSPECT (DETAILED) THE STABILIZER TRIM BALLSCREW, BALLNUT, AND BALLNUT RETURN TUBES. REF TASK 27-450-00-01 | G728: COMPLETED.
A729: 20121-0002 | B729: - | C729: 25-135-00-01 | D729: VQ-BXJ-1 | E729: ROUTINE | F729: VISUALLY CHECK THE FIRST AID KITS. REF TASK 25-135-00-01 | G729: COMPLETED.
A730: 20121-0003 | B730: - | C730: 25-160-00-01 | D730: VQ-BXJ-1 | E730: ROUTINE | F730: OPERATIONALLY CHECK EMERGENCY FLASHLIGHTS. (INCLUDING FLASHLIGHTS IN THE LOWER LOBE ATTENDANT REST, FLIGHT CREW REST AND OVERHEAD FLIGHT CREW/ATTENDANT REST IF INSTALLED). REF TASK 25-160-00-01 | G730: COMPLETED.
A731: 20121-0004 | B731: - | C731: 26-270-00-01 | D731: VQ-BXJ-1 | E731: ROUTINE | F731: INSPECT (DETAILED) LAVATORY WASTE COMPARTMENT FIRE EXTINGUISHER BOTTLES FOR CORRECT WEIGHT AND TEMPERATURE INDICATOR AND EXTINGUISHER FUSIBLE TIPS FOR CONDITION. (INCLUDING BOTTLES IN LAVATORIES IN OVERHEAD FLIGHT CREW/ATTENDANT REST AREAS IF INSTALLED.) REF TASK 26-270-00-01 | G731: COMPLETED.
A732: 20121-0005 | B732: - | C732: 53-868-00-01 | D732: VQ-BXJ-1 | E732: ROUTINE | F732: INTERNAL - ZONAL (GV): BULK CARGO COMPARTMENT PERFORM AN INTERNAL ZONAL INSPECTION (GV) OF THE BULK CARGO COMPARTMENT REF TASK 53-868-00-01 | G732: CANCELLED BY CAMO.
A733: 20121-0006 | B733: - | C733: 12-024-00-01 | D733: VQ-BXJ-1 | E733: ROUTINE | F733: LUBRICATE THE WING AILERON POWER CONTROL UNIT (PCU'S) ROD ENDS AND REACTION LINKS, AND AILERON HINGE FITTINGS. REF TASK 12-024-00-01 | G733: COMPLETED.
A734: 20121-0007 | B734: - | C734: 12-024-00-02 | D734: VQ-BXJ-1 | E734: ROUTINE | F734: LUBRICATE THE WING AILERON POWER CONTROL UNIT (PCU'S) ROD ENDS AND REACTION LINKS, AND AILERON HINGE FITTINGS. REF TASK 12-024-00-02 | G734: COMPLETED.
A735: 20121-0008 | B735: - | C735: 12-026-00-01 | D735: VQ-BXJ-1 | E735: ROUTINE | F735: LUBRICATE FLAPERON POWER CONTROL UNIT (PCU'S) ROD ENDS, HINGE FITTINGS AND PCU YOKE ASSEMBLIES (IF INSTALLED) NOTE: THE NEW FLAPERON PCU YOKE ASSEMBLIES WERE INTRODUCED AT LINE POSITION 357 AND ON OR INCORPORATED THROUGH SB 777-27-0049. EXAMINE THE FLAPERON PCU YOKE ASSEMBLIES FOR GREASE FITTINGS. IF PRESENT, LUBRICATE THE YOKE ASSEMBLIES (4 FITTINGS). REF TASK 12-026-00-01 | G735: COMPLETED.
A736: 20121-0009 | B736: - | C736: 12-026-00-02 | D736: VQ-BXJ-1 | E736: ROUTINE | F736: LUBRICATE FLAPERON POWER CONTROL UNIT (PCU'S) ROD ENDS, HINGE FITTINGS AND PCU YOKE ASSEMBLIES (IF INSTALLED) NOTE: THE NEW FLAPERON PCU YOKE ASSEMBLIES WERE INTRODUCED AT LINE POSITION 357 AND ON OR INCORPORATED THROUGH SB 777-27-0049. EXAMINE THE FLAPERON PCU YOKE ASSEMBLIES FOR GREASE FITTINGS. IF PRESENT, LUBRICATE THE YOKE ASSEMBLIES (4 FITTINGS). REF TASK 12-026-00-02 | G736: COMPLETED.
A737: 20121-0010 | B737: - | C737: 12-006-00-01 | D737: VQ-BXJ-1 | E737: ROUTINE | F737: LUBRICATE THE STABILIZER TRIM BALLSCREW AND BALLSCREW ACTUATOR. REF TASK 12-006-00-01 | G737: COMPLETED.
... A1313: 20124-0015 | B1313: - | C1313: GAES PROCEDURE | D1313: VQ-BXJ-1 | E1313: NONROUTINE | F1313: PERFORM REMOVAL/INSTALLATION OF ACCESS PANELS FOR ZONE 800 AS PER PANEL CLEARANCE SHEETS GAES-148-AMO-REV00-JUL2023 | G1313: COMPLETED.
A1314: 20124-0016 | B1314: 20121-0145 | D1314: VQ-BXJ-1 | E1314: NONROUTINE | F1314: PERFORM CPCP APPLICATION FOR RH MAIN LANDING GEAR WHEEL WELL. | G1314: COMPLETED.
A1315: 20124-0017 | B1315: 20121-0227 | D1315: VQ-BXJ-1 | E1315: NONROUTINE | F1315: PERFORM THE CLEANING OF THE AREA ABOVE PASSENGER COMPARTMENT CEILING FROM STA 246 TO STA 655 LH AND RH SIDES | G1315: COMPLETED.
A1316: 20124-0018 | B1316: 20121-0237 | D1316: VQ-BXJ-1 | E1316: NONROUTINE | F1316: PERFORM THE CLEANING OF THE AREA ABOVE PASSENGER COMPARTMENT CEILING FROM STA 655 TO STA 1035 LH AND RH SIDES | G1316: COMPLETED.
A1317: 20124-0019 | B1317: 20121-0240 | D1317: VQ-BXJ-1 | E1317: NONROUTINE | F1317: PERFORM THE CLEANING OF THE AREA ABOVE PASSENGER COMPARTMENT CEILING FROM STA 1035 TO STA 1434 LH AND RH SIDES | G1317: COMPLETED.
A1318: 20124-0020 | B1318: 20121-0133 | D1318: VQ-BXJ-1 | E1318: NONROUTINE | F1318: PERFORM THE CLEANING OF THE AREA ABOVE PASSENGER COMPARTMENT CEILING FROM STA 1434 TO STA 1832 LH AND RH SIDES | G1318: COMPLETED.
A1319: 20124-0021 | B1319: 20121-0136 | D1319: VQ-BXJ-1 | E1319: NONROUTINE | F1319: PERFORM THE CLEANING OF THE AREA ABOVE PASSENGER COMPARTMENT CEILING FROM STA 1832 TO STA 2150 LH AND RH SIDES | G1319: COMPLETED.
A1320: 20124-0022 | B1320: 20121-0136 | D1320: VQ-BXJ-1 | E1320: NONROUTINE | F1320: PERFORM THE REMOVAL OF CEILING PANELS AND LOWERED CEILING PANEL FROM STA 1832 TO STA 2150 BOTH LH AND RH SIDES | G1320: COMPLETED.
A1321: 20124-0023 | B1321: 20121-0133 | D1321: VQ-BXJ-1 | E1321: NONROUTINE | F1321: PERFORM THE REMOVAL AND INSTALLATION OF CEILING PANELS FROM STA 1434 TO STA 1832 BOTH LH AND RH SIDES | G1321: COMPLETED.
A1322: 20124-0024 | B1322: 20121-0240 | D1322: VQ-BXJ-1 | E1322: NONROUTINE | F1322: PERFORM THE REMOVAL AND INSTALLATION OF CEILING PANELS FROM STA 1035 TO STA 1434 BOTH LH AND RH SIDES | G1322: COMPLETED.
A1323: 20124-0025 | B1323: 20121-0141 | D1323: VQ-BXJ-1 | E1323: NONROUTINE | F1323: C/O APPLICATION ANTI CORROSION PREVENTION AT LH WHEEL WELL AREA . | G1323: COMPLETED.
A1324: 20124-0026 | B1324: 20121-0237 | D1324: VQ-BXJ-1 | E1324: NONROUTINE | F1324: PERFORM THE REMOVAL AND INSTALLATION OF CEILING PANELS FROM STA 655 TO STA 1035 BOTH LH AND RH SIDES | G1324: COMPLETED.
A1325: 20124-0027 | B1325: 20121-0227 | D1325: VQ-BXJ-1 | E1325: NONROUTINE | F1325: PERFORM THE REMOVAL AND INSTALLATION OF CEILING PANELS FROM STA 246 TO STA 655 BOTH LH AND RH SIDES | G1325: COMPLETED.
... A1592: 20124-0294 | B1592: 20121-0478 | D1592: VQ-BXJ-1 | E1592: NONROUTINE | F1592: DUE TO THE SHOP VISIT OF DOOR 3R BACKUP BATTERY PACK,PERFORM REMOVAL OF DOOR 3L BACK UP BAATERY PACK AND INSTALL ON DOOR 3R TEMORARILY TO CARRY OUT FNC OF DOOR 3R BACKUP CIRCUITRY. NORMALIZE THE BACKUP BATTERY PACK ONCE THE TEST IS COMPLETE. | G1592: COMPLETED.
A1593: 20124-0295 | B1593: - | C1593: TLB#0977 ITEM#1 | D1593: VQ-BXJ-1 | E1593: NONROUTINE | F1593: 'TAC' INOP INTERMITTENT DURING FLIGHT | G1593: COMPLETED. ATL# 0977-1 CLOSED.
A1594: 20124-0296 | B1594: - | C1594: TLB#0977 ITEM#2 | D1594: VQ-BXJ-1 | E1594: NONROUTINE | F1594: AUTO SPEED BRAKE INTERMITTENT DURING FLIGHT | G1594: COMPLETED. ATL# 0977 ITEM #2 CLOSED.
A1595: 20125-0001 | B1595: - | C1595: CWR-001 | D1595: VQ-BXJ-1 | E1595: CWR | F1595: PERFORM ONE AIRCRAFT EXTERIOR WASH & ONE AIRCRAFT TECHNICAL WASH. | G1595: COMPLETED.
A1596: 20125-0002 | B1596: - | C1596: CWR-002 | D1596: VQ-BXJ-1 | E1596: CWR | F1596: PERFORM ALL LIFE VEST INVENTORY | G1596: COMPLETED.
A1597: 20125-0003 | B1597: - | C1597: CWR-003 | D1597: VQ-BXJ-1 | E1597: CWR | F1597: PLEASE TAKE ACTION REGARDING BOEING NTO MESSAGE#LET-LET-24-0106-07B. REFER TO ATTACHED TABLE: | G1597: COMPLETED.
A1598: 20126-0001 | B1598: - | C1598: GAES PROCEDURE | D1598: VQ-BXJ-1 | E1598: GENERIC | F1598: MCC + CUSTOMER SUPPORT ONLY | G1598: COMPLETED.
A1599: 20127-0001 | B1599: - | C1599: GAES PROCEDURE | D1599: VQ-BXJ-1 | E1599: GENERIC | F1599: A/C WAITING/TOWING/PREP. | G1599: COMPLETED. CRS ISSUED
A1600: 20127-0002 | B1600: - | C1600: GAES PROCEDURE | D1600: VQ-BXJ-1 | E1600: GENERIC | F1600: WAITING FOR WORK | G1600: COMPLETED. CRS ISSUED
A1601: 20127-0003 | B1601: - | C1601: GAES PROCEDURE | D1601: VQ-BXJ-1 | E1601: GENERIC | F1601: HOUSEKEEPING | G1601: COMPLETED. CRS ISSUED
A1602: 20127-0004 | B1602: - | C1602: GAES PROCEDURE | D1602: VQ-BXJ-1 | E1602: GENERIC | F1602: A/C CHECK MANAGERS ONLY | G1602: COMPLETED. CRS ISSUED
A1603: 20127-0005 | B1603: - | C1603: GAES PROCEDURE | D1603: VQ-BXJ-1 | E1603: GENERIC | F1603: CAT 'C' ONLY | G1603: PROJECT CLOSED.
A1604: 20135-0001 | B1604: - | C1604: WY | D1604: CN-RGA-2 | E1604: ROUTINE | F1604: WEEKLY CHECK REF TASK WY | G1604: COMPLETED
... A2290: 20150-0010 | B2290: - | C2290: GAES PROCEDURE | D2290: CN-RGA-2 | E2290: NONROUTINE | F2290: PERFORM REMOVAL/INSTALLATION OF ACCESS PANELS FOR ZONE 800 AS PER PANEL CLEARANCE SHEETS GAES-148-AMO-REV00-JUL2023 | G2290: COMPLETED.
A2291: 20150-0011 | B2291: 20139-0040 | D2291: CN-RGA-2 | E2291: NONROUTINE | F2291: 4-CHANNEL OPC OF THE CVR FAILED: AREA SOUNDS CANNOT BE NOT HEARD FROM AREA MICROPHONE. PERFORM CORRECTIVE ACTION | G2291: COMPLETED
A2292: 20150-0012 | B2292: 20142-0079 | D2292: CN-RGA-2 | E2292: NONROUTINE | F2292: CARRY OUT REMOVAL/INSTALLATION OF ALL PAX SEATS INCLUDING BC SEATS FOR ACCESS. | G2292: COMPLETED.
A2293: 20150-0013 | B2293: 20138-0058 | D2293: CN-RGA-2 | E2293: NONROUTINE | F2293: DURING HANDSETS CHECK FOUND: 1) HANDSET IS NOT WORKING AT DOOR 5 CREW REST 2) HANDSET IS NOT WORKING AT LEFT U/D DOOR. PERFORM CORRECTIVE ACTION | G2293: COMPLETED.
A2294: 20150-0014 | B2294: 20136-0050 | D2294: CN-RGA-2 | E2294: NONROUTINE | F2294: DURING PASSENGER INFORMATION SIGNS CHECK FOUND: 1) MANY NSFSB SIGNS REQUIRE RELAMPING 2) NSFSB SIGN AT R3 DOOR IS NOT ILLUMINATING 3) NO SMOKING SIGNS AT ZONE E BILLBOARDS ARE NOT ILLUMINATING . PERFORM CORRECTIVE ACTION | G2294: COMPLETED.
A2295: 20150-0015 | B2295: 20136-0050 | D2295: CN-RGA-2 | E2295: NONROUTINE | F2295: DURING LAV OCCUPIED SIGNS CHECK FOUND: 1) FC1-FC4 "LAV OCCUPIED" SIGNS ARE NOT ILLUMINATING IN ZONE E 2) ZONE A "LAV OCCUPIED" SIGN IS NOT ILLUMINATING 3) UD 4U-6U "LAVATORY OCCUPIED" SIGN IS NOT ILLUMINATING. | G2295: COMPLETED.
A2296: 20150-0016 | B2296: 20136-0051 | D2296: CN-RGA-2 | E2296: NONROUTINE | F2296: DURING EMERGENCY LIGHTS OPC FOUND: 1) CEILING EMERGENCY LIGHTS ARE NOT ILLUMINATING AT BOTH LEFT AND RIGHT AISLES AT ZONE E 2)CEILING EMERGENCY LIGHTS ARE NOT ILLUMINATING AT UPPER DECK, ROW 64 ABC 3) OBSERVED WEAK OPERATING TIME OF THE EMERGENCY LIGHTING. PERFORM CORRECTIVE ACTION | G2296: COMPLETED.
A2297: 20150-0017 | B2297: 20135-0001 | D2297: CN-RGA-2 | E2297: NONROUTINE | F2297: DURING OPC OF EXTERNAL LIGHTS -FOUND R/H INBORAD LOGO LIGHT INOPERATIVE. PERFORM RECTIFICATION ACTION. | G2297: COMPLETED
A2298: 20150-0018 | B2298: 20138-0031 | D2298: CN-RGA-2 | E2298: NONROUTINE | F2298: FOUND INTERIOR LIGHTS ARE NOT ILLUMINATING AT LOCATIONS :1) 67-68JKH SIDEWALL LIGHT 2) 23-24ABC SIDEWALL LIGHT 3) 29JKH SIDEWALL LIGHT 4) 01AC CEILING LIGHT 5) 01KH CEILING LIGHT 6) 12-14ABC CEILING LIGHT 7) 37-38ABC CEILING LIGHT 8)30-31JKH CEILING LIGHT 9) 4L DOOR CEILING LIGHT 10) 43-44ABC CEILING LIGHT 11) 57JKH CEILING LIGHT. PERFORM CORRECTIVE ACTION | G2298: COMPLETED.
A2299: 20150-0019 | B2299: - | C2299: TL203275 ITEM A | D2299: CN-RGA-2 | E2299: NONROUTINE | F2299: "DOOR U/D FLT LK' EICAS MESSAGE DURING CLIMB | G2299: COMPLETED. DEFECT CLOSED IN TLB# 203275-A
A2300: 20150-0020 | B2300: 20142-0189 | D2300: CN-RGA-2 | E2300: NONROUTINE | F2300: DURING INSPECTION FOUND LAVATORY SHROUD STRIKER SPRING DAMAGED AT LAV BS2, BS5, BS6, CC21, DC21, DC22, FC4. CARRY OUT CORRECTIVE ACTIONS. | G2300: COMPLETED.
A2301: 20150-0021 | B2301: 20136-0098 | D2301: CN-RGA-2 | E2301: NONROUTINE | F2301: DURING INSPECTION OF LIFEVEST AT 14B, 18K, 14F, 54C PLASTIC COVER AND ADULT SPARE LIFE VEST FOUND DIRTY. | G2301: COMPLETED.
A2302: 20150-0022 | B2302: 20142-0195 | D2302: CN-RGA-2 | E2302: NONROUTINE | F2302: PERFORM THE REMOVAL AND INSTALLATION OF GALLEY G1 FOR ACCESS | G2302: COMPLETED.
A2303: 20150-0023 | B2303: 20142-0195 | D2303: CN-RGA-2 | E2303: NONROUTINE | F2303: PERFORM THE REMOVAL AND INSTALLATION OF GALLEY G2 FOR ACCESS | G2303: COMPLETED.
A2304: 20150-0024 | B2304: 20142-0195 | D2304: CN-RGA-2 | E2304: NONROUTINE | F2304: PERFORM THE REMOVAL AND INSTALLATION OF GALLEY G3 FOR ACCESS | G2304: COMPLETED.
A2305: 20150-0025 | B2305: 20142-0195 | D2305: CN-RGA-2 | E2305: NONROUTINE | F2305: PERFORM THE REMOVAL AND INSTALLATION OF GALLEY G3A FOR ACCESS | G2305: COMPLETED.
A2306: 20150-0026 | B2306: 20142-0195 | D2306: CN-RGA-2 | E2306: NONROUTINE | F2306: PERFORM THE REMOVAL AND INSTALLATION OF GALLEY G3B FOR ACCESS | G2306: COMPLETED.
A2307: 20150-0027 | B2307: 20142-0195 | D2307: CN-RGA-2 | E2307: NONROUTINE | F2307: PERFORM THE REMOVAL AND INSTALLATION OF GALLEY G4 FOR ACCESS | G2307: COMPLETED.
A2308: 20150-0028 | B2308: 20142-0195 | D2308: CN-RGA-2 | E2308: NONROUTINE | F2308: PERFORM THE REMOVAL AND INSTALLATION OF DRY GALLEY AFT OF L2 FOR ACCESS | G2308: COMPLETED.
A2309: 20150-0029 | B2309: 20142-0195 | D2309: CN-RGA-2 | E2309: NONROUTINE | F2309: PERFORM THE REMOVAL AND INSTALLATION OF DRY GALLEY AFT OF R2 FOR ACCESS | G2309: COMPLETED.
A2310: 20150-0030 | B2310: 20142-0195 | D2310: CN-RGA-2 | E2310: NONROUTINE | F2310: PERFORM THE REMOVAL AND INSTALLATION OF GALLEY G5 FOR ACCESS | G2310: COMPLETED.
A2311: 20150-0031 | B2311: 20142-0195 | D2311: CN-RGA-2 | E2311: NONROUTINE | F2311: PERFORM THE REMOVAL AND INSTALLATION OF GALLEY G6 FOR ACCESS | G2311: COMPLETED.
... A2635: 20150-0355 | B2635: 20135-0001 | D2635: CN-RGA-2 | E2635: NONROUTINE | F2635: CMC MESSAGE 32220A NORMAL ANTISKID VALVE-5 FAIL PERFORM TBS AND RECTIFY. | G2635: COMPLETED.
A2636: 20151-0001 | B2636: - | C2636: 4A-21-058-00-A4 | D2636: TF-AMM-1 | E2636: ROUTINE | F2636: RESTORE (OFF-AIRCRAFT) PRIMARY OR SECONDARY AFT EQUIPMENT COOLING FAN PN 645980-1 REF TASK 4A-21-058-00-A4 | G2636: COMPLETED
A2637: 20151-0002 | B2637: - | C2637: 4A-46-060A01 | D2637: TF-AMM-1 | E2637: ROUTINE | F2637: EFB PERIODIC INSPECTIONS REF TASK 4A-46-060A01 | G2637: TASK CANCELLED BY CUSTOMER DUE TO SYSTEM HAS BEEN DEACTIVATED.
A2638: 20151-0003 | B2638: - | C2638: 4N-11-000-00-01 | D2638: TF-AMM-1 | E2638: ROUTINE | F2638: CONDITION CHECK, EXTERIOR PAINT AND MARKINGS REF TASK 4N-11-000-00-01 | G2638: COMPLETED
A2639: 20151-0004 | B2639: - | C2639: 4N-11-001-01-01 | D2639: TF-AMM-1 | E2639: ROUTINE | F2639: CHECK CONDITION OF INTERIOR PLACARDS. REF TASK 4N-11-001-01-01 | G2639: COMPLETED.
A2640: 20151-0005 | B2640: - | C2640: 4N-12-002-00-01 | D2640: TF-AMM-1 | E2640: ROUTINE | F2640: CHANGE ENGINE 1 INTEGRATED DRIVE GENERATOR OIL. REF TASK 4N-12-002-00-01 | G2640: COMPLETED
A2641: 20151-0006 | B2641: - | C2641: 4N-12-002-00-02 | D2641: TF-AMM-1 | E2641: ROUTINE | F2641: CHANGE ENGINE 2 INTEGRATED DRIVE GENERATOR OIL. REF TASK 4N-12-002-00-02 | G2641: COMPLETED
A2642: 20151-0007 | B2642: - | C2642: 4N-12-002-00-03 | D2642: TF-AMM-1 | E2642: ROUTINE | F2642: CHANGE ENGINE 3 INTEGRATED DRIVE GENERATOR OIL. REF TASK 4N-12-002-00-03 | G2642: COMPLETED
A2643: 20151-0008 | B2643: - | C2643: 4N-12-002-00-04 | D2643: TF-AMM-1 | E2643: ROUTINE | F2643: CHANGE ENGINE 4 INTEGRATED DRIVE GENERATOR OIL. REF TASK 4N-12-002-00-04 | G2643: COMPLETED
A2644: 20151-0009 | B2644: - | C2644: 4N-12-010-00-01 | D2644: TF-AMM-1 | E2644: ROUTINE | F2644: LUBRICATE ACCESS PANEL ZIPPERS ON THE AFT BULKHEAD IN THE LOWER LOBE BULK CARGO COMPARTMENT AND ZIPPERS IN THE CEILING LINING OF THE FORWARD CARGO COMPARTMENT (IF INSTALLED). REF TASK 4N-12-010-00-01 | G2644: COMPLETED
A2645: 20151-0010 | B2645: - | C2645: 4N-12-016-00-01 | D2645: TF-AMM-1 | E2645: ROUTINE | F2645: SERVICE THE LEFT WING LEADING EDGE FLAP PDUS WITH OIL. REF TASK 4N-12-016-00-01 | G2645: COMPLETED.
...

Sheet GAES EEF Registry
A1: EEF Number | B1: NRC Number | C1: AC Type | D1: ATA | E1: Project No. | F1: Subject | G1: Remarks | H1: Location | I1: EEF Status | J1: Link | K1: Link Path | L1: Man Hours | M1: Chargeable to Customer? | N1: Customer Name | O1: Inspection Source Task | P1: RC# | Q1: Open Date | R1: Assigned Engineering Engineer | S1: OPEN/Continuation Raised by Production Dates | T1: Answer provided by Engineering Dates | U1: OEM Communication Reference | V1: GAES EO | W1: Manual limits (OUT / WITHIN) | X1: Back-up Engineer | Y1: Project Status | Z1: EEF Priority | AA1: Latest Processing | AB1: Project Status2
A2: 2025-0627 | B2: 20315-0752 | C2: B747-400 | D2: 53 | E2: ER-BAJ-2 | F2: RH WING INBD FLAP O/B RIB AT GUIDE ROLLER FITTING CRACKED | G2: Fitting replacement | H2: WITH PRODUCTION | I2: CLOSED | J2: =IF(K2="","",HYPERLINK(K2, "Link")) -> Link | K2: K:\ENGINEERING\Engineering Enquiry Forms\2025 EEF PDF FORMAT (SCAN)\EEF 2025-0627 ER-BAJ-2 | L2: 5 | M2: YES | N2: AERO TRANSCARGO | P2: =IF((VLOOKUP(B2,'Work Card Inquiry'!A:E,5,FALSE))="NONROUTINE",VLOOKUP(B2,'Work Card Inquiry'!A:E,2,FALSE), B2) -> #N/A | Q2: 45910 | R2: AMARNATH
A3: 2025-0626 | B3: 20315-0751 | C3: B747-400 | D3: 57 | E3: ER-BAJ-2 | F3: LH WING INBD FLAP O/B RIB AT GUIDE ROLLER FITTING CRACKED | G3: Fitting replacement | H3: WITH PRODUCTION | I3: CLOSED | J3: =IF(K3="","",HYPERLINK(K3, "Link")) -> Link | K3: K:\ENGINEERING\Engineering Enquiry Forms\2025 EEF PDF FORMAT (SCAN)\EEF 2025-0626 ER-BAJ-2 | L3: 5 | M3: YES | N3: AERO TRANSCARGO | P3: =IF((VLOOKUP(B3,'Work Card Inquiry'!A:E,5,FALSE))="NONROUTINE",VLOOKUP(B3,'Work Card Inquiry'!A:E,2,FALSE), B3) -> #N/A | Q3: 45910 | R3: AMARNATH
A4: 2025-0625 | B4: 20790-0093 | C4: B777-200 | D4: 25 | E4: ER-BOY-1 | F4: MID AND AFT GALLEY SPIGOT LEVER INTERCHANGEABILTIY | G4: Clarification sent to OEM, Due to the P/N CS-340-12 (FAUCET) is not referenced in CMM 25-04-57. | H4: WITH PRODUCTION | I4: CLOSED | J4: =IF(K4="","",HYPERLINK(K4, "Link")) -> Link | K4: K:\ENGINEERING\Engineering Enquiry Forms\2025 EEF PDF FORMAT (SCAN)\EEF 2025-0625 ER-BOY-1 | L4: 4 | M4: YES | N4: AQULINE INTERNATIONAL | P4: =IF((VLOOKUP(B4,'Work Card Inquiry'!A:E,5,FALSE))="NONROUTINE",VLOOKUP(B4,'Work Card Inquiry'!A:E,2,FALSE), B4) -> #N/A | Q4: 45909 | R4: AMARNATH
A5: 2025-0624 | B5: 20790-0169 | C5: B777-200 | D5: 72 | E5: ER-BOY-1 | F5: FAN BLADE LUBRICATION - MATERIAL INTERCHANGEABILITY FOR OMAT 876A | G5: w Boeing to confirm correct material. ETS 13 Sep # Jeewana Request has been sent to Customer Waiting for response # Jeewana UNDER ENGINEERING EVALUATION | H5: WITH OEM | I5: OPEN | J5: =IF(K5="","",HYPERLINK(K5, "Link")) -> Link | K5: T:\3. Departmental Folders\10 Technical Services\ENGINEERING\Engineering Enquiry Forms\2025 EEF PDF FORMAT (SCAN)\EEF 2025-0624 ER-BOY-1 | L5: TBD | M5: YES | N5: AQULINE INTERNATIONAL | O5: TASK: 72-346-01 | P5: =IF((VLOOKUP(B5,'Work Card Inquiry'!A:E,5,FALSE))="NONROUTINE",VLOOKUP(B5,'Work Card Inquiry'!A:E,2,FALSE), B5) -> #N/A | Q5: 45908 | R5: JEEWANA
A6: 2025-0623 | B6: 20790-0087 | C6: B777-200 | D6: 57 | E6: ER-BOY-1 | F6: LH FLAPERON COVER LIP DOOR FITTING REPLCEMENT | G6: Blind Bolt removal & Replacement instructions provided # Jeewana | H6: WITH PRODUCTION | I6: CLOSED | J6: =IF(K6="","",HYPERLINK(K6, "Link")) -> Link | K6: T:\3. Departmental Folders\10 Technical Services\ENGINEERING\Engineering Enquiry Forms\2025 EEF PDF FORMAT (SCAN)\EEF 2025-0623 ER-BOY-1 | L6: 3 | M6: YES | N6: AQULINE INTERNATIONAL | O6: TASK: 57-520-01 | P6: =IF((VLOOKUP(B6,'Work Card Inquiry'!A:E,5,FALSE))="NONROUTINE",VLOOKUP(B6,'Work Card Inquiry'!A:E,2,FALSE), B6) -> #N/A | Q6: 45904 | R6: JEEWANA
A7: 2025-0622 | B7: 20790-0089CWR-002 | C7: B777-200 | D7: 25 | E7: ER-BOY-1 | F7: ALL LAVATORY FUACET'S ARE LEAKING - PRE/POST CONFIG LISTED IN CMM - P/N IDENTIFICATION | G7: #Subhash 3. CMM received, orrder Part IAW CMM 2.Requested CMM from customer 1. Under Evaluation | H7: WITH PRODUCTION | I7: CLOSED | J7: =IF(K7="","",HYPERLINK(K7, "Link")) -> Link | K7: T:\3. Departmental Folders\10 Technical Services\ENGINEERING\Engineering Enquiry Forms\2025 EEF PDF FORMAT (SCAN)\EEF 2025-0622 ER-BOY-1 | L7: 5 | M7: YES | N7: AQULINE INTERNATIONAL | O7: CWR-002 | P7: =IF((VLOOKUP(B7,'Work Card Inquiry'!A:E,5,FALSE))="NONROUTINE",VLOOKUP(B7,'Work Card Inquiry'!A:E,2,FALSE), B7) -> #N/A | Q7: 45903 | R7: SUBHASH
A8: 2025-0621 | B8: 20790-0094 | C8: B777-200 | D8: 25 | E8: ER-BOY-1 | F8: FWD GALLEY WATER LINE HOSE MISSING AND CONFIGURATION NOT MARCHING WITH CMM - P/N IDENTIFICATION - REPLACEMENT | G8: #Chandu (#SCA-2025-09-001452) wOEM, clamp P/N & Hose Assy P/N received from SAFRAN | H8: WITH PRODUCTION | I8: CLOSED | J8: =IF(K8="","",HYPERLINK(K8, "Link")) -> Link | K8: T:\3. Departmental Folders\10 Technical Services\ENGINEERING\Engineering Enquiry Forms\2025 EEF PDF FORMAT (SCAN)\EEF 2025-0621 ER-BOY-1 | L8: 6 | M8: YES | N8: AQULINE INTERNATIONAL | O8: CWR-002 | P8: =IF((VLOOKUP(B8,'Work Card Inquiry'!A:E,5,FALSE))="NONROUTINE",VLOOKUP(B8,'Work Card Inquiry'!A:E,2,FALSE), B8) -> #N/A | Q8: 45900 | R8: CHANDU
A9: 2025-0620 | B9: 21069-0002 | C9: B777-200 | D9: 53 | E9: ER-BOY-1 | F9: FUSELAGE EXTERNAL SKIN AND SHEAR CLIPS - AT STA 1916 & BETWEEN STGR 42R & 43R - DENT | G9: w Prod awaiting doubler material # Jeewana 4. Production request for deviation to the doubler materials & request sent to customer for approval 3. Doubler & Filler thickness provided to Production. 2. Additional Clarification requested by production. 1. Initial Instructions issued to perform repair as per SRM 53-00-01 R04 | H9: WITH PRODUCTION | I9: OPEN | J9: =IF(K9="","",HYPERLINK(K9, "Link")) -> Link | K9: T:\3. Departmental Folders\10 Technical Services\ENGINEERING\Engineering Enquiry Forms\2025 EEF PDF FORMAT (SCAN)\EEF 2025-0620 ER-BOY-1 | L9: 6 | M9: YES | N9: AQULINE INTERNATIONAL | O9: SR-BOY-53-221 | P9: =IF((VLOOKUP(B9,'Work Card Inquiry'!A:E,5,FALSE))="NONROUTINE",VLOOKUP(B9,'Work Card Inquiry'!A:E,2,FALSE), B9) -> #N/A | Q9: 45897 | R9: JEEWANA
A10: 2025-0619 | B10: 21000-0052 | C10: B747-400 | D10: 52 | E10: ER-BOS-1 | F10: APU DOOR SKIN REPAIR - FABRICATION REQUEST | G10: Answered | H10: WITH PRODUCTION | I10: CLOSED | J10: =IF(K10="","",HYPERLINK(K10, "Link")) -> Link | K10: T:\3. Departmental Folders\10 Technical Services\ENGINEERING\Engineering Enquiry Forms\2025 EEF PDF FORMAT (SCAN)\EEF 2025-0619 ER-BOS-1 | L10: TBD | M10: NO | N10: AQULINE INTERNATIONAL | O10: 53-924-01 | P10: =IF((VLOOKUP(B10,'Work Card Inquiry'!A:E,5,FALSE))="NONROUTINE",VLOOKUP(B10,'Work Card Inquiry'!A:E,2,FALSE), B10) -> #N/A | Q10: 45896 | R10: JEEWANA
A11: 2025-0618 | B11: 20790-0097 | C11: B777-200 | D11: 57 | E11: ER-BOY-1 | F11: LH WING TE LOWER ACCESS PANEL SUPPORT BEAM BTW IRSS 805 TO 850 AND CHORD ASSY AT 831.76 - CRACK - REPLACEMENT | G11: # Chandu ETS 27 Aug Replace as per DWG | H11: WITH PRODUCTION | I11: CLOSED | J11: =IF(K11="","",HYPERLINK(K11, "Link")) -> Link | K11: T:\3. Departmental Folders\10 Technical Services\ENGINEERING\Engineering Enquiry Forms\2025 EEF PDF FORMAT (SCAN)\EEF 2025-0618 ER-BOY-1 | L11: 3 | M11: YES | N11: AQULINE INTERNATIONAL | O11: 57-868-01-01 | P11: =IF((VLOOKUP(B11,'Work Card Inquiry'!A:E,5,FALSE))="NONROUTINE",VLOOKUP(B11,'Work Card Inquiry'!A:E,2,FALSE), B11) -> #N/A | Q11: 45895 | R11: CHANDU
A12: 2025-0617 | B12: 20790-0035 | C12: B777-200 | D12: 57 | E12: ER-BOY-1 | F12: CORROSSION ON LH WING LWR SURFACE SKIN BTWN WS1035 AND WS1055 | G12: w V1 for approval document 1.Under Evaluation 2. Damage report in progress, requested drawing for skin thickness. 3. Requested production for additional NDT fot UT (ETS 28-Aug). 4. Reported to customer 5. Awaiting approval for PO from customer 6. Quote approved, With V1 for repair 7. Repair completed, reported to V1 | H12: WITH DER | I12: OPEN | J12: =IF(K12="","",HYPERLINK(K12, "Link")) -> Link | K12: T:\3. Departmental Folders\10 Technical Services\ENGINEERING\Engineering Enquiry Forms\2025 EEF PDF FORMAT (SCAN)\EEF 2025-0617 ER-BOY-1 | L12: 4 | M12: YES | N12: AQULINE INTERNATIONAL | O12: 57-840-01-01 | P12: =IF((VLOOKUP(B12,'Work Card Inquiry'!A:E,5,FALSE))="NONROUTINE",VLOOKUP(B12,'Work Card Inquiry'!A:E,2,FALSE), B12) -> #N/A | Q12: 45894 | R12: SUBHASH
A13: 2025-0616 | B13: 20790-0033 | C13: B777-200 | D13: 57 | E13: ER-BOY-1 | F13: CORROSSION ON LH WING LWR SURFACE SKIN BTWN WS 916 AND STA WS942 | G13: w V1 for approval document 1. Damage report in progress, requested drawing for skin thickness. 2. Requested production for additional NDT fot UT 3. Reported to customer 4. Hangar for additional information. 5. Reported to customer. 6. Awaiting approval for PO from customer 7. Quote approved, With V1 for repair 8. Repair completed, reported to V1 | H13: WITH DER | I13: OPEN | J13: =IF(K13="","",HYPERLINK(K13, "Link")) -> Link | K13: T:\3. Departmental Folders\10 Technical Services\ENGINEERING\Engineering Enquiry Forms\2025 EEF PDF FORMAT (SCAN)\EEF 2025-0616 ER-BOY-1 | L13: 4 | M13: YES | N13: AQULINE INTERNATIONAL | O13: 57-840-01-01 | P13: =IF((VLOOKUP(B13,'Work Card Inquiry'!A:E,5,FALSE))="NONROUTINE",VLOOKUP(B13,'Work Card Inquiry'!A:E,2,FALSE), B13) -> #N/A | Q13: 45894 | R13: SUBHASH
A14: 2025-0615 | B14: 21017-0114 | C14: B747-400F | D14: 32 | E14: 9H-AKF-1 | F14: RH WING LANDING GEAR UP-LOCK QUADRANT -REPLACEMENT PROCEDURE CLARIFICATION | G14: Replace as per CMM 32-32-23 | H14: WITH PRODUCTION | I14: CLOSED | J14: =IF(K14="","",HYPERLINK(K14, "Link")) -> Link | K14: T:\3. Departmental Folders\10 Technical Services\ENGINEERING\Engineering Enquiry Forms\2025 EEF PDF FORMAT (SCAN)\EEF 2025-0615 9H-AKF-1 | L14: 3 | M14: NO | N14: AIR ATLANTA EUROPE | O14: 4N-20-004-00-02 | P14: =IF((VLOOKUP(B14,'Work Card Inquiry'!A:E,5,FALSE))="NONROUTINE",VLOOKUP(B14,'Work Card Inquiry'!A:E,2,FALSE), B14) -> #N/A | Q14: 45894 | R14: CHANDU
A15: 2025-0614 | B15: 20790-0061 | C15: B777-200 | D15: 53 | E15: ER-BOY-1 | F15: LOWER FUSELAGE SKIN STA 1546.5,S-49R - CORROSSION | G15: #Subash Approval document issued to production Repair completed, reported to V1. w Prod, Final repair instruction received to leave it as-is. Repair in progress. | H15: WITH PRODUCTION | I15: CLOSED | J15: =IF(K15="","",HYPERLINK(K15, "Link")) -> Link | K15: T:\3. Departmental Folders\10 Technical Services\ENGINEERING\Engineering Enquiry Forms\2025 EEF PDF FORMAT (SCAN)\EEF 2025-0614 ER-BOY-1 | L15: 6 | M15: YES | N15: AQULINE INTERNATIONAL | O15: 53-894-00-01 | P15: =IF((VLOOKUP(B15,'Work Card Inquiry'!A:E,5,FALSE))="NONROUTINE",VLOOKUP(B15,'Work Card Inquiry'!A:E,2,FALSE), B15) -> #N/A | Q15: 45894 | R15: SUBHASH
A16: 2025-0613 | B16: 21000-0013 | C16: B747-400 | D16: 38 | E16: ER-BOS-1 | F16: LWR FUSELAGE FWD DRAIN MAST - CORROSION - P/N CLARIFICATION | G16: Requested CMM from customer. Replace as per AIPC 38-31-01-01 | H16: WITH PRODUCTION | I16: CLOSED | J16: =IF(K16="","",HYPERLINK(K16, "Link")) -> Link | K16: T:\3. Departmental Folders\10 Technical Services\ENGINEERING\Engineering Enquiry Forms\2025 EEF PDF FORMAT (SCAN)\EEF 2025-0613 ER-BOS-1 | L16: 2 | M16: NO | N16: AQULINE INTERNATIONAL | O16: 53-804-01 | P16: =IF((VLOOKUP(B16,'Work Card Inquiry'!A:E,5,FALSE))="NONROUTINE",VLOOKUP(B16,'Work Card Inquiry'!A:E,2,FALSE), B16) -> #N/A | Q16: 45893 | R16: SUBHASH
A17: 2025-0612 | B17: 21054-0003 | C17: B747-400F | D17: 73 | E17: 9H-AKF-1 | F17: Engine #4 ECU INSTALLATION LIMITATIONS - SB CLARIFICATION | G17: Accepteable to install, as there are no restrictions in SB | H17: WITH PRODUCTION | I17: CLOSED | J17: =IF(K17="","",HYPERLINK(K17, "Link")) -> Link | K17: T:\3. Departmental Folders\10 Technical Services\ENGINEERING\Engineering Enquiry Forms\2025 EEF PDF FORMAT (SCAN)\EEF 2025-0612 9H-AKF-1 | L17: 4 | M17: NO | N17: AIR ATLANTA EUROPE | O17: R-72-131-02-01 | P17: =IF((VLOOKUP(B17,'Work Card Inquiry'!A:E,5,FALSE))="NONROUTINE",VLOOKUP(B17,'Work Card Inquiry'!A:E,2,FALSE), B17) -> #N/A | Q17: 45893 | R17: CHANDU
A18: 2025-0611 | B18: 20790-0090 | C18: B777-200 | D18: 53 | E18: ER-BOY-1 | F18: BELLY FAIRING SUPPORT BRACKETS CRACKED AT STA 1035 AND 1245 - CRACK - REPLACEMENT | G18: # Chandu ETS 27 Aug Replace as per DWG | H18: WITH PRODUCTION | I18: CLOSED | J18: =IF(K18="","",HYPERLINK(K18, "Link")) -> Link | K18: T:\3. Departmental Folders\10 Technical Services\ENGINEERING\Engineering Enquiry Forms\2025 EEF PDF FORMAT (SCAN)\EEF 2025-0611 ER-BOY-1 | L18: 3 | M18: YES | N18: AQULINE INTERNATIONAL | O18: 53-890-00-01 | P18: =IF((VLOOKUP(B18,'Work Card Inquiry'!A:E,5,FALSE))="NONROUTINE",VLOOKUP(B18,'Work Card Inquiry'!A:E,2,FALSE), B18) -> #N/A | Q18: 45891 | R18: CHANDU
A19: 2025-0610 | B19: 20790-0062 | C19: B777-200 | D19: 53 | E19: ER-BOY-1 | F19: SUPPORT BRACKET ON STRUCTURE ASSY-AFT FAIRING STA 1476 TO 1546.5 @ BL 0 - CRACKS | G19: Drawing requested from customer The damaged Bracket is identified as P/N: 149W5182 Part To Bre Replaced # Jeewana | H19: WITH PRODUCTION | I19: CLOSED | J19: =IF(K19="","",HYPERLINK(K19, "Link")) -> Link | K19: T:\3. Departmental Folders\10 Technical Services\ENGINEERING\Engineering Enquiry Forms\2025 EEF PDF FORMAT (SCAN)\EEF 2025-0610 ER-BOY | L19: 4 | M19: YES | N19: AQULINE INTERNATIONAL | O19: TASK: 53-894-00 | P19: =IF((VLOOKUP(B19,'Work Card Inquiry'!A:E,5,FALSE))="NONROUTINE",VLOOKUP(B19,'Work Card Inquiry'!A:E,2,FALSE), B19) -> #N/A | Q19: 45889 | R19: JEEWANA
A20: 2025-0609 | B20: 20790-0023 | C20: B777-200 | D20: 53 | E20: ER-BOY-1 | F20: UNDER WING FAIRING SPORT LOWER ACCESS FAIRING195ML FWD ATTACHMENT BRACKET - CORROSION | G20: Damage part is identified on Assy P/N 149W2171-1, specifically affecting Part P/N 149W2171-3 manufactured from BAC1518-1070 (7075-T6); as the assembly, part, and extrusion are not available, the customer has confirmed that the Frame Assembly P/N: 149W2171-1 will be supplied # Jeewana | H20: WITH PRODUCTION | I20: CLOSED | J20: =IF(K20="","",HYPERLINK(K20, "Link")) -> Link | K20: T:\3. Departmental Folders\10 Technical Services\ENGINEERING\Engineering Enquiry Forms\2025 EEF PDF FORMAT (SCAN)\EEF 2025-0609 ER-BOY | L20: 4 | M20: YES | N20: AQULINE INTERNATIONAL | O20: TASK: 53-800-00-03 | P20: =IF((VLOOKUP(B20,'Work Card Inquiry'!A:E,5,FALSE))="NONROUTINE",VLOOKUP(B20,'Work Card Inquiry'!A:E,2,FALSE), B20) -> #N/A | Q20: 45889 | R20: JEEWANA
A21: 2025-0608 | B21: 21017-0072 | C21: B747-400F | D21: 54 | E21: 9H-AKF-1 | F21: MULTIPLE DENTS ON ENG# 3 ACOUSTIC PANEL LOWER SKIN | G21: # Jeewana ETS 29 Aug w Prod, Final repair instructions received from V1. Repair completed. FAA 8110-3 Recived & EEF Closed | H21: WITH PRODUCTION | I21: CLOSED | J21: =IF(K21="","",HYPERLINK(K21, "Link")) -> Link | K21: T:\3. Departmental Folders\10 Technical Services\ENGINEERING\Engineering Enquiry Forms\2025 EEF PDF FORMAT (SCAN)\EEF 2025-0608 9H-AKF-1 | L21: 4 | M21: YES | N21: AIR ATLANTA EUROPE | O21: 4N-71-802-01-03 | P21: =IF((VLOOKUP(B21,'Work Card Inquiry'!A:E,5,FALSE))="NONROUTINE",VLOOKUP(B21,'Work Card Inquiry'!A:E,2,FALSE), B21) -> #N/A | Q21: 45888 | R21: JEEWANA
A22: 2025-0607 | B22: 21017 - 0106 | C22: B747-400F | D22: 53 | E22: 9H-AKF-1 | F22: MULTIPLE CRACKS ON FUSELAGE SKIN - LAP SPLICE UPPER FASTENER ROW BETWEEN STA 1440 AND STA 1480 AT S-23L | G22: w Prod, Final repair instructions received from V1. Repair completed & reported back to V1. Final approval & AMOC Received | H22: WITH PRODUCTION | I22: CLOSED | J22: =IF(K22="","",HYPERLINK(K22, "Link")) -> Link | K22: T:\3. Departmental Folders\10 Technical Services\ENGINEERING\Engineering Enquiry Forms\2025 EEF PDF FORMAT (SCAN)\EEF 2025-0607 9H-AKF-1 | L22: 30 | M22: YES | N22: AIR ATLANTA EUROPE | O22: FAA AD 2024-19-01 | P22: =IF((VLOOKUP(B22,'Work Card Inquiry'!A:E,5,FALSE))="NONROUTINE",VLOOKUP(B22,'Work Card Inquiry'!A:E,2,FALSE), B22) -> #N/A | Q22: 45887 | R22: AMARNATH
... A26: 2025-0603 | B26: 20956-0009 | C26: B747-400F | D26: 32 | E26: TF-AKG-9 | F26: LH Wing Landing Gear Door - FWD Seal Retainer - Crack | G26: (SR# V1-02919) #Jeewana 2. w V1 initial reapir proposal rejected. Raw material and part N/A. 1. w V1, Rejected Repair proposal Customer Is preferred to replace the door | H26: WITH PRODUCTION | I26: CLOSED | J26: =IF(K26="","",HYPERLINK(K26, "Link")) -> Link | K26: T:\3. Departmental Folders\10 Technical Services\ENGINEERING\Engineering Enquiry Forms\2025 EEF PDF FORMAT (SCAN)\EEF 2025-0603 TF-AKG-9 | L26: 3 | M26: YES | N26: AIR ATLANTA ICELANDIC | O26: CWR-009 | P26: =IF((VLOOKUP(B26,'Work Card Inquiry'!A:E,5,FALSE))="NONROUTINE",VLOOKUP(B26,'Work Card Inquiry'!A:E,2,FALSE), B26) -> 20956-0009 | Q26: 45873 | R26: JEEWANA
A27: 2025-0602 | B27: 20911-0124 | C27: B747-400F | D27: 52 | E27: TF-AKG-9 | F27: AFT CARGO DOOR CLOSING SWITH BRACKET - CORROSION - REPLACEMENT P/N IDENTIFICATION | G27: Replace the affected bracket P/N 65B04719-20. | H27: WITH PRODUCTION | I27: CLOSED | J27: =IF(K27="","",HYPERLINK(K27, "Link")) -> Link | K27: T:\3. Departmental Folders\10 Technical Services\ENGINEERING\Engineering Enquiry Forms\2025 EEF PDF FORMAT (SCAN)\EEF 2025-0602 TF-AKG-9 | L27: 5 | M27: YES | N27: AIR ATLANTA ICELANDIC | O27: MPD-52-410-00-02 | P27: =IF((VLOOKUP(B27,'Work Card Inquiry'!A:E,5,FALSE))="NONROUTINE",VLOOKUP(B27,'Work Card Inquiry'!A:E,2,FALSE), B27) -> 20909-0493 | Q27: 45866 | R27: SUBHASH | T27: 45867 | W27: OUT | Z27: NORMAL | AA27: ANSWERED
A28: 2025-0601 | B28: 20988-0056 | C28: B777-200 | D28: 53 | E28: 4L-MWB-1 | F28: FUSELAGE SKIN STA 164.75 - 188.5 ABOVE WINDOW 2 - PUNCTURE (FOD DAMAGE) - DOUBLER REPAIR | G28: BCS MA6-MA6-25-0018 # Jeewana ETS TBD 4. w Prod to close the access, top coat restoration, Final EEF issued. 3. Repair prfrmd, with no deviation from (-5B msg) FAA 8100-9 received. 2. w Boeing - Damage report and repair proposal submitted. 1. w Hangar - Preliminary instructions for damage removal and inspection. | H28: WITH PRODUCTION | I28: CLOSED | J28: =IF(K28="","",HYPERLINK(K28, "Link")) -> Link | K28: T:\3. Departmental Folders\10 Technical Services\ENGINEERING\Engineering Enquiry Forms\2025 EEF PDF FORMAT (SCAN)\EEF 2025-0601 4L-MWB-1 | L28: 15 | M28: YES | N28: MY WAY AIRLINES | O28: 53-898-00-02 | P28: =IF((VLOOKUP(B28,'Work Card Inquiry'!A:E,5,FALSE))="NONROUTINE",VLOOKUP(B28,'Work Card Inquiry'!A:E,2,FALSE), B28) -> 20985-0395 | Q28: 45861 | R28: JEEWANA | W28: OUT | X28: Dmitry | AA28: ANSWERED
A29: 2025-0600 | B29: 20985-0425 | C29: B777-200 | D29: 54 | E29: 4L-MWB-1 | F29: LH AND RH PYLON STRUCT AFT FAIRING GAP COVER STRIPS REPLACEMENT - EO Request | G29: 1. EO issued IAW SRM 54-51-70. #AMARNATH | H29: WITH PRODUCTION | I29: CLOSED | J29: =IF(K29="","",HYPERLINK(K29, "Link")) -> Link | K29: T:\3. Departmental Folders\10 Technical Services\ENGINEERING\Engineering Enquiry Forms\2025 EEF PDF FORMAT (SCAN)\EEF 2025-0600 4L-MWB | L29: 1 | M29: YES | N29: MY WAY AIRLINES | O29: SRM 54-51-70 | P29: =IF((VLOOKUP(B29,'Work Card Inquiry'!A:E,5,FALSE))="NONROUTINE",VLOOKUP(B29,'Work Card Inquiry'!A:E,2,FALSE), B29) -> 20985-0425 | Q29: 45859 | R29: AMARNATH | AA29: ANSWERED
A30: 2025-0599 | B30: 20994-0001 | C30: A320-232P2F | D30: 32 | E30: SU-SKD-1 | F30: LH MLG SIDE STAY - CORROSION - BRUSH PLATING PER PCS-2141 IS REQUIRED - ALTERNATE PLATING PROCEDURE REQUEST | G30: 1. Re-protection as per SRM is acceptable by Safran, if the solution meets the requirements of AMS2451/4. #JEEWANA | H30: WITH PRODUCTION | I30: CLOSED | J30: =IF(K30="","",HYPERLINK(K30, "Link")) -> Link | K30: T:\3. Departmental Folders\10 Technical Services\ENGINEERING\Engineering Enquiry Forms\2025 EEF PDF FORMAT (SCAN)\EEF 2025-0599 SU-SKD-1 | L30: 3 | M30: YES | N30: SKY VISION AIRLINES | O30: RDAS-SLS-2025-06-1833 | P30: =IF((VLOOKUP(B30,'Work Card Inquiry'!A:E,5,FALSE))="NONROUTINE",VLOOKUP(B30,'Work Card Inquiry'!A:E,2,FALSE), B30) -> - | Q30: 45856 | R30: JEEWANA | S30: A: 7/18/2025 | W30: TBD
A31: 2025-0598 | B31: 20956-0005 | C31: B747-400F | D31: 78 | E31: TF-AKG-9 | F31: ENG#1 LH TRANSLATING COWL UPPER BEAVERTAIL FAIRING - POTENTIAL CRACK | G31: 3. Repair as per CMM 2. NDT reports from Production #SUBHASH, 1. PAINT HAS BEEN REMOVED AND CONFIRMED THE SEPERATION OF THE UPPER BEAVERTAIL FAIRING AND SKIN. | H31: WITH PRODUCTION | I31: CLOSED | J31: =IF(K31="","",HYPERLINK(K31, "Link")) -> Link | K31: T:\3. Departmental Folders\10 Technical Services\ENGINEERING\Engineering Enquiry Forms\2025 EEF PDF FORMAT (SCAN)\EEF 2025-0598 TF-AKG-9 | L31: 6 | M31: YES | N31: AIR ATLANTA ICELANDIC | O31: CWR-005 | P31: =IF((VLOOKUP(B31,'Work Card Inquiry'!A:E,5,FALSE))="NONROUTINE",VLOOKUP(B31,'Work Card Inquiry'!A:E,2,FALSE), B31) -> 20956-0005 | Q31: 45855 | R31: SUBHASH | Y31: WIP | AA31: ANSWERED
A32: 2025-0597 | B32: 20905-0085 | C32: B747-400F | D32: 57 | E32: 9H-FLM-1 | F32: LH NAVIGATION LIGHT LENS - P/N INTERCHANGEABILITY CLARIFICATION | G32: 2. CORRECT REPLACEMENT PART IS LENS ASSEMBLY P/N: 284U7032-21. 1. IT IS NOT ACCEPTABLE TO INSTALL PMA LENS PIN: N284U7032-71 DUE TO SIGNIFICANT CONFIGURATION DEVIATION. #JEEWANA | H32: WITH PRODUCTION | I32: CLOSED | J32: =IF(K32="","",HYPERLINK(K32, "Link")) -> Link | K32: T:\3. Departmental Folders\10 Technical Services\ENGINEERING\Engineering Enquiry Forms\2025 EEF PDF FORMAT (SCAN)\EEF 2025-0597 9H-FLM-1 | L32: 3 | M32: YES | N32: AIR ATLANTA EUROPE LTD | O32: MPD-57-806-01-01 | P32: =IF((VLOOKUP(B32,'Work Card Inquiry'!A:E,5,FALSE))="NONROUTINE",VLOOKUP(B32,'Work Card Inquiry'!A:E,2,FALSE), B32) -> 20903-0336 | R32: JEEWANA
A33: 2025-0596 | B33: 20930-0015 20930-0074 | C33: A320-214 | D33: 53 | E33: A6-AOJ | F33: FUSELAGE SKIN - EXISTING (NOT REGISTERED) REWORKS MULTIPLE FINDINGS AFTER PAINT STRIPPING | G33: w Airbus for RDAF 81620479_003_2025#A Recived TD_81620479_005_2025 received & all reworked areas found to be acceptable as per TD. Damage noted while prfrmng SRM 51-75-11 Acid paint stripper before re-painting EEF Closed Dossie# 81620479 # Jeewana | H33: WITH PRODUCTION | I33: CLOSED | J33: =IF(K33="","",HYPERLINK(K33, "Link")) -> Link | K33: K:\ENGINEERING\Engineering Enquiry Forms\2025 EEF PDF FORMAT (SCAN)\EEF 2025-0596 A6-AOJ-1 | L33: 7 | M33: YES | N33: AIR ARABIA PJSC | O33: 3854599 (PAINT) SRM 51-75-11 | P33: =IF((VLOOKUP(B33,'Work Card Inquiry'!A:E,5,FALSE))="NONROUTINE",VLOOKUP(B33,'Work Card Inquiry'!A:E,2,FALSE), B33) -> #N/A | Q33: 45841 | R33: JEEWANA | S33: A: 7/3/2025 D: 7/10/2025 | T33: B: 7/4/2025 D: 7/11/2025 E:11-Jul-2025 | W33: OUT | AA33: ANSWERED
A34: 2025-0595 | B34: 20905-0176 | C34: B747-400F | D34: 53 | E34: 9H-FLM-1 | F34: FUSELAGE STRINGER SPLICE - STA 1740, S-35L - CRACK - P/N IDENTIFICATION | G34: (BCS# AID-AE8-25-0009-01C) # Chandu 1. w Production, to replace the damaged part with a new STRINGER CHANNEL - SPLICE P/N is 65B06895-13 as per BCS. | H34: WITH PRODUCTION | I34: CLOSED | J34: =IF(K34="","",HYPERLINK(K34, "Link")) -> Link | K34: T:\3. Departmental Folders\10 Technical Services\ENGINEERING\Engineering Enquiry Forms\2025 EEF PDF FORMAT (SCAN)\EEF 2025-0595 9H-FLM-1 | L34: 5 | M34: YES | N34: AIR ATLANTA EUROPE LTD | O34: B47-AD2002-23-15 SB 747-53A2487 | P34: =IF((VLOOKUP(B34,'Work Card Inquiry'!A:E,5,FALSE))="NONROUTINE",VLOOKUP(B34,'Work Card Inquiry'!A:E,2,FALSE), B34) -> 20904-0002 | Q34: 45841 | R34: CHANDU | U34: AID-AE8-25-0009-01C | W34: OUT
A35: 2025-0594 | B35: 20905-0016 | C35: B747-400F | D35: 78 | E35: 9H-FLM-1 | F35: ENG#2 RH THRUST REVERSER - LOWER ANGLE GEAR BOX MOUNT BRACKET - CRACKED | H35: WITH PRODUCTION | I35: CLOSED | J35: =IF(K35="","",HYPERLINK(K35, "Link")) -> Link | K35: T:\3. Departmental Folders\10 Technical Services\ENGINEERING\Engineering Enquiry Forms\2025 EEF PDF FORMAT (SCAN)\EEF 2025-0594 9H-FLM-1/ | L35: 2 | M35: NO | N35: AIR ATLANTA EUROPE LTD | O35: MPD-78-131-13-02 | P35: =IF((VLOOKUP(B35,'Work Card Inquiry'!A:E,5,FALSE))="NONROUTINE",VLOOKUP(B35,'Work Card Inquiry'!A:E,2,FALSE), B35) -> 20903-0377 | Q35: 45839 | R35: SUBHASH | T35: 45839 | W35: WITHIN | X35: CHANDU | AA35: ANSWERED
A36: 2025-0593 | B36: 20948-0002 | C36: B747-400F | D36: 52 | E36: 9H-MSK | F36: RH WING INBD STRUT DOOR PUNCTURE REPAIR PARTS FABRICATION FORM REQUEST | G36: Answered | H36: WITH PRODUCTION | I36: CLOSED | J36: =IF(K36="","",HYPERLINK(K36, "Link")) -> Link | K36: T:\3. Departmental Folders\10 Technical Services\ENGINEERING\Engineering Enquiry Forms\2025 EEF PDF FORMAT (SCAN)\EEF 2025-0593 9H-MSK-11/ | L36: 2 | M36: YES | N36: QUICK LINK AVIATION SERVICES (FZC) | O36: CWR-002 ITEM#6 | P36: =IF((VLOOKUP(B36,'Work Card Inquiry'!A:E,5,FALSE))="NONROUTINE",VLOOKUP(B36,'Work Card Inquiry'!A:E,2,FALSE), B36) -> 20948-0002 | Q36: 45833 | R36: JEEWANA | S36: B: 6/25/2025 | T36: A: 6/25/2025 | U36: N/A | W36: WITHIN | AA36: ANSWERED
A37: 2025-0592 | B37: 20949-0028 | C37: A321 | D37: 57 | E37: UK32120-4 | F37: VENT SURGE TANK VORTEX GENERATOR INSTALLED | G37: Answered | H37: WITH PRODUCTION | I37: CLOSED | J37: =IF(K37="","",HYPERLINK(K37, "Link")) -> Link | K37: T:\3. Departmental Folders\10 Technical Services\ENGINEERING\Engineering Enquiry Forms\2025 EEF PDF FORMAT (SCAN)\EEF 2025-0592 UK32120-4/ | L37: 3 | M37: YES | N37: SAM AIR LLC | O37: 281200-01-1 | P37: =IF((VLOOKUP(B37,'Work Card Inquiry'!A:E,5,FALSE))="NONROUTINE",VLOOKUP(B37,'Work Card Inquiry'!A:E,2,FALSE), B37) -> 20949-0028 | Q37: 45832 | R37: AMARNATH | S37: B: 6/30/2025 | T37: 45833 | U37: 81613747 | W37: WITHIN | AA37: ANSWERED
A38: 2025-0591 | B38: 20952-0014 | C38: A321 | D38: 54 | E38: UK32120-4 | F38: ENG#1 INLET COWL INNER BAREL AT 6-O CLOCK - ACOUSTIC MESH DAMAGE | G38: Answered | H38: WITH PRODUCTION | I38: CLOSED | J38: =IF(K38="","",HYPERLINK(K38, "Link")) -> Link | K38: T:\3. Departmental Folders\10 Technical Services\ENGINEERING\Engineering Enquiry Forms\2025 EEF PDF FORMAT (SCAN)\EEF 2025-0591 UK32120-4/ | L38: 5 | M38: YES | N38: SAM AIR LLC | O38: A321-Transit-01 | P38: =IF((VLOOKUP(B38,'Work Card Inquiry'!A:E,5,FALSE))="NONROUTINE",VLOOKUP(B38,'Work Card Inquiry'!A:E,2,FALSE), B38) -> 20949-0083 | Q38: 45830 | R38: SUBHASH | T38: B: 25-Jun-2025 C: 25-Jun-2025 D: 29-Jun-2025 | U38: ROHR/S240/2025_A COLLINS CV25-08525 | W38: OUT | X38: JEEWANA | AA38: ANSWERED
A39: 2025-0590 | B39: 20818-0001 | C39: B747-400F | D39: 52 | E39: CN-RGA-3 | F39: SB 747-32-2536_RO- PART FABRICATION REQUEST | G39: Answered | H39: WITH PRODUCTION | I39: CLOSED | J39: =IF(K39="","",HYPERLINK(K39, "Link")) -> Link | K39: T:\3. Departmental Folders\10 Technical Services\ENGINEERING\Engineering Enquiry Forms\2025 EEF PDF FORMAT (SCAN)\EEF 2025-0590 CN-RGA-3/ | L39: 2 | M39: NO | N39: ROYAL AIR MAROC | O39: SB 747-32-2536 R0 | P39: =IF((VLOOKUP(B39,'Work Card Inquiry'!A:E,5,FALSE))="NONROUTINE",VLOOKUP(B39,'Work Card Inquiry'!A:E,2,FALSE), B39) -> 20818-0001 | Q39: 45828 | R39: SUBHASH | T39: 45831 | W39: WITHIN | X39: AMARNATH | AA39: ANSWERED
A40: 2025-0589 | B40: 20889-0009 to 20889-0067 | C40: A320-214 | D40: 53 | E40: A6-AOI | F40: FUSELAGE SKIN - EXISTING (NOT REGISTERED) REWORKS MULTIPLE FINDINGS AFTER PAINT STRIPPING | G40: Answered Damage noted while prfrmng SRM 51-75-11 Acid paint stripper before re-painting | H40: WITH PRODUCTION | I40: CLOSED | J40: =IF(K40="","",HYPERLINK(K40, "Link")) -> Link | K40: T:\3. Departmental Folders\10 Technical Services\ENGINEERING\Engineering Enquiry Forms\2025 EEF PDF FORMAT (SCAN)\EEF 2025-0589 A6-AOI-1/ | L40: 5 | M40: YES | N40: AIR ARABIA PJSC | O40: 3854598 (PAINT) SRM 51-75-11 | P40: =IF((VLOOKUP(B40,'Work Card Inquiry'!A:E,5,FALSE))="NONROUTINE",VLOOKUP(B40,'Work Card Inquiry'!A:E,2,FALSE), B40) -> #N/A | Q40: 16-6-2025 | R40: JEEWANA | S40: A: 6/16/2025 D: 6/22/2025 | T40: B: 6/17/2025 C: 6/22/2025 E: 6/26/2025 | U40: Airbus Dossier 81611250 | W40: OUT | X40: CHANDU | AA40: ANSWERED
A41: 2025-0588 | B41: 20845-0003 | C41: B747-400F | D41: 28 | E41: CN-RGA-3 | F41: MAIN FUEL TANK # 1 FQIS WIRE - DAMAGE - SLEEVE REPAIR PER SWPM | G41: # Chandu 1. w Production, to replace the wire bundle will be the feseable option instead of the Sleeve repair per SWPM 20-14-12, as the sleve repair requires FAA oversight approval which will take 30-60days. | H41: WITH PRODUCTION | I41: CLOSED | J41: =IF(K41="","",HYPERLINK(K41, "Link")) -> Link | K41: T:\3. Departmental Folders\10 Technical Services\ENGINEERING\Engineering Enquiry Forms\2025 EEF PDF FORMAT (SCAN)\EEF 2025-0588 CN-RGA-3/ | L41: 9 | M41: YES | N41: ROYAL AIR MAROC | O41: CWR-003 | P41: =IF((VLOOKUP(B41,'Work Card Inquiry'!A:E,5,FALSE))="NONROUTINE",VLOOKUP(B41,'Work Card Inquiry'!A:E,2,FALSE), B41) -> 20845-0003 | Q41: 45824 | R41: CHANDU | S41: A: 16-Jun-2025 | T41: B: 17-Jun-2025 | U41: RAM-MRC-25-0017 | W41: OUT | AA41: ANSWERED
A42: 2025-0587 | B42: 20885-0010 | C42: B747-400F | D42: 53 | E42: CN-RGA-3 | F42: FUSELAGE SKIN AT STA 741, STRG 26 - MULTIPLE DENTS ADJACENT TO REPAIR DOUBLER | G42: Answered. Unique dents not registered | H42: WITH PRODUCTION | I42: CLOSED | J42: =IF(K42="","",HYPERLINK(K42, "Link")) -> Link | K42: T:\3. Departmental Folders\10 Technical Services\ENGINEERING\Engineering Enquiry Forms\2025 EEF PDF FORMAT (SCAN)\EEF 2025-0587 CN-RGA-3/ | L42: 5 | M42: YES | N42: ROYAL AIR MAROC | O42: AMES/MP/10-014 | P42: =IF((VLOOKUP(B42,'Work Card Inquiry'!A:E,5,FALSE))="NONROUTINE",VLOOKUP(B42,'Work Card Inquiry'!A:E,2,FALSE), B42) -> 20885-0010 | Q42: 45819 | R42: SUBHASH | S42: 45833 | T42: B: 19-Jun-2025 | U42: RAM-MRC-25-0014 | W42: OUT | AA42: ANSWERED
A43: 2025-0586 | B43: 20823-0165 | C43: B747-400F | D43: 54 | E43: CN-RGA-3 | F43: ENG#2 OUTBD FAIRING REPAIR - FABRICATION REQUEST | G43: Answered | H43: WITH PRODUCTION | I43: CLOSED | J43: =IF(K43="","",HYPERLINK(K43, "Link")) -> Link | K43: T:\3. Departmental Folders\10 Technical Services\ENGINEERING\Engineering Enquiry Forms\2025 EEF PDF FORMAT (SCAN)\EEF 2025-0586 CN-RGA-3/ | L43: 2 | M43: NO | N43: ROYAL AIR MAROC | O43: 54-812-00-02 | P43: =IF((VLOOKUP(B43,'Work Card Inquiry'!A:E,5,FALSE))="NONROUTINE",VLOOKUP(B43,'Work Card Inquiry'!A:E,2,FALSE), B43) -> 20808-0217 | Q43: 45818 | R43: SUBHASH | T43: 45818 | W43: WITHIN | AA43: ANSWERED
A44: 2025-0585 | B44: 20845-0003 | C44: B747-400F | D44: 57 | E44: CN-RGA-3 | F44: RIB REMOVAL AND WINDHEILD REPLACEMENT TO BE PERFORMED WHILE AIRCRAFT IS ON JACK | H44: WITH PRODUCTION | I44: CLOSED | J44: =IF(K44="","",HYPERLINK(K44, "Link")) -> Link | K44: T:\3. Departmental Folders\10 Technical Services\ENGINEERING\Engineering Enquiry Forms\2025 EEF PDF FORMAT (SCAN)\EEF 2025-0585 CN-RGA-3/ | L44: 4 | M44: YES | N44: ROYAL AIR MAROC | O44: CWR-003 | P44: =IF((VLOOKUP(B44,'Work Card Inquiry'!A:E,5,FALSE))="NONROUTINE",VLOOKUP(B44,'Work Card Inquiry'!A:E,2,FALSE), B44) -> 20845-0003 | Q44: 45817 | R44: AMARNATH | T44: 45819 | W44: OUT | AA44: ANSWERED
A45: 2025-0584 | B45: 20667-1174 | C45: B747-400F | D45: 57 | E45: TF-AMU-17 | F45: RH WING SPOILER #7 INBD AREA DAMAGE - FABRICATION REQUEST | G45: Answered | H45: WITH PRODUCTION | I45: CLOSED | J45: =IF(K45="","",HYPERLINK(K45, "Link")) -> Link | K45: T:\3. Departmental Folders\10 Technical Services\ENGINEERING\Engineering Enquiry Forms\2025 EEF PDF FORMAT (SCAN)\EEF 2025-0584 TF-AMU-17/ | L45: 2 | M45: NO | N45: AIR ATLANTA ICELANDIC | O45: CWR-003 ITEM 3&4 | P45: =IF((VLOOKUP(B45,'Work Card Inquiry'!A:E,5,FALSE))="NONROUTINE",VLOOKUP(B45,'Work Card Inquiry'!A:E,2,FALSE), B45) -> 20666-0010 | Q45: 45812 | R45: SUBHASH | T45: 45812 | W45: WITHIN | AA45: ANSWERED
A46: 2025-0583 | B46: 20817-0022 | C46: B747-400F | D46: 53 | E46: CN-RGA-3 | F46: STRECHED UPPER DECK FRAME AND TENSION TIE MISLOCATED ANGLES - FABRICATION REQUEST | G46: Answered. Fabrication Checklist and Form provided. | H46: WITH PRODUCTION | I46: CLOSED | J46: =IF(K46="","",HYPERLINK(K46, "Link")) -> Link | K46: T:\3. Departmental Folders\10 Technical Services\ENGINEERING\Engineering Enquiry Forms\2025 EEF PDF FORMAT (SCAN)\EEF 2025-0583 CN-RGA-3/ | L46: 2 | M46: NO | N46: ROYAL AIR MAROC | O46: 2016-05-12 (m) SB 747-53A2507 | P46: =IF((VLOOKUP(B46,'Work Card Inquiry'!A:E,5,FALSE))="NONROUTINE",VLOOKUP(B46,'Work Card Inquiry'!A:E,2,FALSE), B46) -> 20817-0022 | Q46: 45810 | R46: SUBHASH | T46: 45811 | W46: WITHIN | AA46: ANSWERED
A47: 2025-0582 | B47: 20667-1168 | C47: B747-400F | D47: 78 | E47: TF-AMU-17 | F47: EBG# 2, LH TR, ACTUATOR CASTING FITTING - CRACK | G47: Answered | H47: WITH PRODUCTION | I47: CLOSED | J47: =IF(K47="","",HYPERLINK(K47, "Link")) -> Link | K47: T:\3. Departmental Folders\10 Technical Services\ENGINEERING\Engineering Enquiry Forms\2025 EEF PDF FORMAT (SCAN)\EEF 2025-0582 TF-AMU-17/ | L47: 6 | M47: YES | N47: AIR ATLANTA ICELANDIC | O47: MPD-78-131-16-02 | P47: =IF((VLOOKUP(B47,'Work Card Inquiry'!A:E,5,FALSE))="NONROUTINE",VLOOKUP(B47,'Work Card Inquiry'!A:E,2,FALSE), B47) -> 20664-1558 | Q47: 45809 | R47: JEEWANA | S47: A: 6/1/2025 | T47: B: 6/3/2025 | U47: V1-02839 | W47: OUT | AA47: WIP
A48: 2025-0581 | B48: 20865-0095 | C48: A320-214 | D48: 25 | E48: CN-NMQ-1 | F48: GALLEY FAUCET - REMOVAL AND INSTALLATION PROCEDURE | G48: Answered | H48: WITH PRODUCTION | I48: CLOSED | J48: =IF(K48="","",HYPERLINK(K48, "Link")) -> Link | K48: T:\3. Departmental Folders\10 Technical Services\ENGINEERING\Engineering Enquiry Forms\2025 EEF PDF FORMAT (SCAN)\EEF 2025-0581 CN-NMQ-1/ | L48: 3 | M48: YES | N48: AIR ARABIA MAROC S.A. | O48: 4160568 | P48: =IF((VLOOKUP(B48,'Work Card Inquiry'!A:E,5,FALSE))="NONROUTINE",VLOOKUP(B48,'Work Card Inquiry'!A:E,2,FALSE), B48) -> 20862-0202 | Q48: 45806 | R48: SUBHASH | W48: WITHIN | AA48: ANSWERED
A49: 2025-0580 | B49: 20667-0307 | C49: B747-400F | D49: 57 | E49: TF-AMU-17 | F49: RH WING O/B AFTFLAP O/B LOWER SURFACE FOUND SURFACE DENTS - FABRICATION REQUEST | G49: ANSWERED | H49: WITH PRODUCTION | I49: CLOSED | J49: =IF(K49="","",HYPERLINK(K49, "Link")) -> Link | K49: T:\3. Departmental Folders\10 Technical Services\ENGINEERING\Engineering Enquiry Forms\2025 EEF PDF FORMAT (SCAN)\EEF 2025-0580 TF-AMU-17/ | L49: 2 | M49: NO | N49: AIR ATLANTA ICELANDIC | O49: MPD-57-954-01-01 | P49: =IF((VLOOKUP(B49,'Work Card Inquiry'!A:E,5,FALSE))="NONROUTINE",VLOOKUP(B49,'Work Card Inquiry'!A:E,2,FALSE), B49) -> 20664-1460 | Q49: 45804 | R49: SUBHASH | T49: B 27-MAY-2025 | W49: WITHIN | AA49: ANSWERED
A50: 2025-0579 | B50: 20823-0302 | C50: B747-400F | D50: 53 | E50: CN-RGA-3 | F50: AFT CARGO CEILING PANEL SUPPORT ASSY INTERCORSAL STA 1800 - 1920 - DAMAGE - SPLICE REPAIR | G50: (BCS# RAM-MRC-25-0018) #Chandu 4. w Production, RDR recived & issued. 3. w Production, Repair by trim and discard the damaged section and repair with a spilce repair per BCS. 2. w Boeing, Due to unavailability of part, damage report with th erepair proposal submitted to Boeing. 1. w Production, Due to the extint of the damage, replacement is the feseable option. | H50: WITH PRODUCTION | I50: CLOSED | J50: =IF(K50="","",HYPERLINK(K50, "Link")) -> Link | K50: T:\3. Departmental Folders\10 Technical Services\ENGINEERING\Engineering Enquiry Forms\2025 EEF PDF FORMAT (SCAN)\EEF 2025-0579 CN-RGA-3/ | L50: 10 | M50: YES | N50: ROYAL AIR MAROC | O50: 53-852-01 | P50: =IF((VLOOKUP(B50,'Work Card Inquiry'!A:E,5,FALSE))="NONROUTINE",VLOOKUP(B50,'Work Card Inquiry'!A:E,2,FALSE), B50) -> 20810-0098 | Q50: 45802 | R50: CHANDU | S50: A: 25-May-2025 D: 25-Jun-2025 | T50: B: 26-May-2025 C: 16-Jun-2025 | U50: RAM-MRC-25-0018 | W50: OUT | AA50: ANSWERED
A51: 2025-0578 | B51: 20823-0242 | C51: B747-400F | D51: 57 | E51: CN-RGA-3 | F51: LH WING FIX TE BEAM UPPER CORD B/W WBL 235.200- WBL 353.000 - CORROSION | G51: w Boeing for RDR. EO 0240-2025 issued to Prod for repair. Typical Case, Similar References: 2025-0578, 2025-0413 NOT TYPICAL Materials to USE (10 Days LT, if avail): CHORD PROFILE: BAC1506-2633, AL 7075-T6511 Extr, per AMS-QQ-A-200/11. (12 feet stock length) (BCS RAM-MRC-25-0011) # Dmitry | H51: WITH PRODUCTION | I51: CLOSED | J51: =IF(K51="","",HYPERLINK(K51, "Link")) -> Link | K51: T:\3. Departmental Folders\10 Technical Services\ENGINEERING\Engineering Enquiry Forms\2025 EEF PDF FORMAT (SCAN)\EEF 2025-0578 CN-RGA-3/ | L51: 10 | M51: YES | N51: ROYAL AIR MORACO | O51: 57-440-00-03 | P51: =IF((VLOOKUP(B51,'Work Card Inquiry'!A:E,5,FALSE))="NONROUTINE",VLOOKUP(B51,'Work Card Inquiry'!A:E,2,FALSE), B51) -> 20808-0226 | Q51: 45800 | R51: DMITRY | S51: A: 23-May-2025 | T51: B: 25-May-2025 | U51: RAM-MRC-25-0011 | V51: 0240-2025 | W51: OUT | X51: AMARNATH | Z51: NORMAL | AA51: ANSWERED
A52: 2025-0577 | B52: 20880-0049 | C52: A320-214 | D52: 53 | E52: CN-NMQ-1 | F52: AFT CARGO FLOOR PANELS - DAMAGE - FABRICATION FORM REQUEST (152CF, 152BF, 152FF, 152EF, 152NF, 152MF, 152RF, 152QF, 151LF, 151GF, 151QF, 151RF, 151MF, 151NF, 151HF, 151JF, 151FF, 151EF, 151BF AND 151CF.) | G52: #Chandu 1.w Production, Fabrication Form and Check List Issued to production. | H52: WITH PRODUCTION | I52: CLOSED | J52: =IF(K52="","",HYPERLINK(K52, "Link")) -> Link | K52: T:\3. Departmental Folders\10 Technical Services\ENGINEERING\Engineering Enquiry Forms\2025 EEF PDF FORMAT (SCAN)\EEF 2025-0577 CN-NMQ-1/ | L52: 1 | M52: NO | N52: AIR ARABIA MAROC S.A. | O52: CWR-005-2 | P52: =IF((VLOOKUP(B52,'Work Card Inquiry'!A:E,5,FALSE))="NONROUTINE",VLOOKUP(B52,'Work Card Inquiry'!A:E,2,FALSE), B52) -> 20880-0049 | Q52: 45800 | R52: CHANDU | S52: A: 23-May-2025 | T52: B: 23-May-2025 | U52: NIL | W52: WITHIN | AA52: ANSWERED
A53: 2025-0576 | B53: 20880-0048 | C53: A320-214 | D53: 53 | E53: CN-NMQ-1 | F53: FWD CARGO FLOOR PANELS - DAMAGE - FABRICATION FORM REQUEST (131KF, 131JF, 131HF, 131GF, 131BF, 131AF, 132GF, 132FF, 132JF AND 132KF.) | G53: #Chandu 1.w Production, Fabrication Form and Check List Issued to production. | H53: WITH PRODUCTION | I53: CLOSED | J53: =IF(K53="","",HYPERLINK(K53, "Link")) -> Link | K53: T:\3. Departmental Folders\10 Technical Services\ENGINEERING\Engineering Enquiry Forms\2025 EEF PDF FORMAT (SCAN)\EEF 2025-0576 CN-NMQ-1/ | L53: 1 | M53: NO | N53: AIR ARABIA MAROC S.A. | O53: CWR-005-1 | P53: =IF((VLOOKUP(B53,'Work Card Inquiry'!A:E,5,FALSE))="NONROUTINE",VLOOKUP(B53,'Work Card Inquiry'!A:E,2,FALSE), B53) -> 20880-0048 | Q53: 45800 | R53: CHANDU | S53: A: 23-May-2025 | T53: B: 23-May-2025 | U53: NIL | W53: WITHIN | AA53: ANSWERED
A54: 2025-0575 | B54: 20747-0294 | C54: A319-115 | D54: 25 | E54: A6-CJE-1 | F54: WINDOW SHADE ABD ETHERNET CONNECTOR REPLACEMENT - INSTALLATION PROCEDURE | G54: ANSWERED | H54: WITH PRODUCTION | I54: CLOSED | J54: =IF(K54="","",HYPERLINK(K54, "Link")) -> Link | K54: T:\3. Departmental Folders\10 Technical Services\ENGINEERING\Engineering Enquiry Forms\2025 EEF PDF FORMAT (SCAN)\EEF 2025-0575 A6-CJE-1/ | L54: 2 | M54: NO | N54: EMIRATES | O54: NDD/002 | P54: =IF((VLOOKUP(B54,'Work Card Inquiry'!A:E,5,FALSE))="NONROUTINE",VLOOKUP(B54,'Work Card Inquiry'!A:E,2,FALSE), B54) -> - | Q54: 45799 | R54: SUBHASH | T54: 45804 | W54: OUT | AA54: ANSWERED
A55: 2025-0574 | B55: 20823-0268 | C55: B747-400F | D55: 57 | E55: CN-RGA-3 | F55: RH WING UPPER SKIN BETWEEN FRAME STA 1350 AND WBL 128 - CORROSION | G55: with Engineering, Paper work closure in progress. (BCS RAM-MRC-25-0006) # Jeewana ETS 13 Jul | H55: WITH PRODUCTION | I55: CLOSED | J55: =IF(K55="","",HYPERLINK(K55, "Link")) -> Link | K55: T:\3. Departmental Folders\10 Technical Services\ENGINEERING\Engineering Enquiry Forms\2025 EEF PDF FORMAT (SCAN)\EEF 2025-0574 CN-RGA-3/ | L55: 45 | M55: YES | N55: ROYAL AIR MAROC | O55: 57-440-00-07 | P55: =IF((VLOOKUP(B55,'Work Card Inquiry'!A:E,5,FALSE))="NONROUTINE",VLOOKUP(B55,'Work Card Inquiry'!A:E,2,FALSE), B55) -> 20808-0230 | Q55: 45799 | R55: AMARNATH | T55: R: 6/29/2025 | U55: RAM-MRC-25-0006 | W55: OUT | X55: JEEWANA | AA55: WIP
A56: 2025-0573 | B56: 20823-0335 | C56: B747-400F | D56: 53 | E56: CN-RGA-3 | F56: ADF ANTENNA DOUBLER AT STA 1283-1350 STGR 1L - 1R - CORROSION | G56: 1. Parts fabricated and SMAL & RDR for coating deviation available. 2. With RAM for primary structure local fabrication concession & minor mod approval. (BCS RAM-MRC-25-0019) # Jeewana | H56: WITH PRODUCTION | I56: CLOSED | J56: =IF(K56="","",HYPERLINK(K56, "Link")) -> Link | K56: T:\3. Departmental Folders\10 Technical Services\ENGINEERING\Engineering Enquiry Forms\2025 EEF PDF FORMAT (SCAN)\EEF 2025-0573 CN-RGA-3/ | L56: 9 | M56: YES | N56: ROYAL AIR MAROC | O56: AMM 34-57-02-004-001 AMM 05-00-01-211-801 AMM 34-57-02-404-012 | P56: =IF((VLOOKUP(B56,'Work Card Inquiry'!A:E,5,FALSE))="NONROUTINE",VLOOKUP(B56,'Work Card Inquiry'!A:E,2,FALSE), B56) -> 20809-0367 | Q56: 45798 | R56: AMARNATH | T56: 45818 | U56: RAM-MRC-25-0019 | W56: OUT | X56: JEEWANA | AA56: ANSWERED
A57: 2025-0572 | B57: 20747-0094 | C57: A319-115 | D57: 28 | E57: A6-CJE-1 | F57: ADDITIONAL CENTER TANK AUTOMATIC TRANSFER SYSTEM FAILED | G57: Answered | H57: WITH PRODUCTION | I57: CLOSED | J57: =IF(K57="","",HYPERLINK(K57, "Link")) -> Link | K57: T:\3. Departmental Folders\10 Technical Services\ENGINEERING\Engineering Enquiry Forms\2025 EEF PDF FORMAT (SCAN)\EEF 2025-0572 A6-CJE-1/ | L57: 6 | M57: YES | N57: EMIRATES | O57: MDD/113 | P57: =IF((VLOOKUP(B57,'Work Card Inquiry'!A:E,5,FALSE))="NONROUTINE",VLOOKUP(B57,'Work Card Inquiry'!A:E,2,FALSE), B57) -> - | Q57: 45798 | R57: JEEWANA | S57: A: 5/21/2025 | T57: B: 5/22/2025 D: 5/26/2025 F: 5/27/2025 | W57: OUT | AA57: WIP
A58: 2025-0571 | B58: 20667-0616 | C58: B747-400F | D58: 28 | E58: TF-AMU-17 | F58: JETTISON PUMP HOUSING INSTALLATION GREASE - USAGE CLARIFICATION | G58: ANSWERED 20665-0067 -(INSULATION RESISTANCE CHECK ON FUEL PUMPS) | H58: WITH PRODUCTION | I58: CLOSED | J58: =IF(K58="","",HYPERLINK(K58, "Link")) -> Link | K58: T:\3. Departmental Folders\10 Technical Services\ENGINEERING\Engineering Enquiry Forms\2025 EEF PDF FORMAT (SCAN)\EEF 2025-0571 TF-AMU-17/ | L58: 2 | M58: NO | N58: AIR ATLANTA ICELANDIC | O58: B47-AD97-03-17 747-28A2194 R1 | P58: =IF((VLOOKUP(B58,'Work Card Inquiry'!A:E,5,FALSE))="NONROUTINE",VLOOKUP(B58,'Work Card Inquiry'!A:E,2,FALSE), B58) -> 20665-0067 | Q58: 45797 | R58: SUBHASH | T58: 45802 | W58: WITHIN | Z58: NORMAL | AA58: ANSWERED
A59: 2025-0570 | B59: 20823-0279 | C59: B747-400 | D59: 53 | E59: CN-RGA-3 | F59: CRACK ON STRINGER CLIP AT STA 1140 STGR 10 | G59: SMAL APPROVAL RECEIVED, Material found with 5 - days LT. Fabrication Form and inspection check list issued to production. Notifed to quality due to primary structure element fabrication. | H59: WITH PRODUCTION | I59: CLOSED | J59: =IF(K59="","",HYPERLINK(K59, "Link")) -> Link | K59: T:\3. Departmental Folders\10 Technical Services\ENGINEERING\Engineering Enquiry Forms\2025 EEF PDF FORMAT (SCAN)\EEF 2025-0570 CN-RGA-3/ | L59: 6 | M59: YES | N59: ROYAL AIR MAROC | O59: 2016-05-12 (m) | P59: =IF((VLOOKUP(B59,'Work Card Inquiry'!A:E,5,FALSE))="NONROUTINE",VLOOKUP(B59,'Work Card Inquiry'!A:E,2,FALSE), B59) -> 20817-0022 | Q59: 45798 | R59: AMARNATH | S59: C: 04-Jun-2025 | T59: D: 11-Jun-2025 | U59: RAM-RAM-25-0224 | W59: WITHIN | X59: CHANDU | AA59: ANSWERED
A60: 2025-0569 | B60: 20823-0194 | C60: B747-400 | D60: 53 | E60: CN-RGA-3 | F60: FUSELAGE UNDERWING FAIRING RH REAR SPAR UPPER FITTING - CORROSION - REPLACEMENT | G60: (BCS RAM-MRC-25-0015) # Chandu 3.w Production, RDR received & Issued. 2.w Production, Due to unavailability of the part and respective materials, Fabricate with alt extrusion BAC1507-48711 as per BCS. 1.w Production, Replace the damaged Fitting P/N 69B11816-7 as per DWG 65B10533 & 69B11816. | H60: WITH PRODUCTION | I60: CLOSED | J60: =IF(K60="","",HYPERLINK(K60, "Link")) -> Link | K60: T:\3. Departmental Folders\10 Technical Services\ENGINEERING\Engineering Enquiry Forms\2025 EEF PDF FORMAT (SCAN)\EEF 2025-0569 CN-RGA-3/ | L60: 10 | M60: YES | N60: ROYAL AIR MAROC | O60: 53-866-01 | P60: =IF((VLOOKUP(B60,'Work Card Inquiry'!A:E,5,FALSE))="NONROUTINE",VLOOKUP(B60,'Work Card Inquiry'!A:E,2,FALSE), B60) -> 20809-0271 | Q60: 45798 | R60: CHANDU | S60: C: 04-Jun-2025 | T60: D: 17-Jun-2025 | U60: RAM-MRC-25-0015 | W60: OUT | AA60: ANSWERED
A61: 2025-0568 | B61: 20857-0031 | C61: B737-700 | D61: 57 | E61: 4L-MWC-2 | F61: RH Wing OUTBD AFT FLAP LOWER SKIN - DELAMINATION - FABRICATION FORM FOR COMPOSITE REPAIR | G61: # Chandu 1.w Production, Fabrication Form and Inpection check list issued to perform repair per SRM 57-53-01 R04 & SRM 51-70-10 | H61: WITH PRODUCTION | I61: CLOSED | J61: =IF(K61="","",HYPERLINK(K61, "Link")) -> Link | K61: T:\3. Departmental Folders\10 Technical Services\ENGINEERING\Engineering Enquiry Forms\2025 EEF PDF FORMAT (SCAN)\EEF 2025-0568 4L-MWC-2/ | L61: 1 | M61: NO | N61: MYWAY AIRLINES CO LTD | O61: 57-070-02-01 | P61: =IF((VLOOKUP(B61,'Work Card Inquiry'!A:E,5,FALSE))="NONROUTINE",VLOOKUP(B61,'Work Card Inquiry'!A:E,2,FALSE), B61) -> 20855-0062 | Q61: 45798 | R61: CHANDU | S61: A: 21-May-2025 | T61: B: 21-May-2025 | U61: NIL | W61: WITHIN | AA61: ANSWERED
A62: 2025-0567 | B62: 20857-0030 | C62: B737-700 | D62: 57 | E62: 4L-MWC-2 | F62: LH Wing OUTBD AFT FLAP LOWER SKIN - DELAMINATION - FABRICATION FORM FOR COMPOSITE REPAIR | G62: # Chandu 1.w Production, Fabrication Form and Inpection check list issued to perform repair per SRM 57-53-01 R04 & SRM 51-70-10 | H62: WITH PRODUCTION | I62: CLOSED | J62: =IF(K62="","",HYPERLINK(K62, "Link")) -> Link | K62: T:\3. Departmental Folders\10 Technical Services\ENGINEERING\Engineering Enquiry Forms\2025 EEF PDF FORMAT (SCAN)\EEF 2025-0567 4L-MWC-2/ | L62: 1 | M62: NO | N62: MYWAY AIRLINES CO LTD | O62: 57-070-01-01 | P62: =IF((VLOOKUP(B62,'Work Card Inquiry'!A:E,5,FALSE))="NONROUTINE",VLOOKUP(B62,'Work Card Inquiry'!A:E,2,FALSE), B62) -> 20855-0061 | Q62: 45798 | R62: CHANDU | S62: A: 21-May-2025 | T62: B: 21-May-2025 | U62: NIL | W62: WITHIN | AA62: ANSWERED
A63: 2025-0566 | B63: 20872-0002 | C63: B777-200 | D63: 55 | E63: C5-ECT-2 | F63: LH HORIZONTAL STAB TIP AND ELEVATOR - DAMAGE - REPLACEMENT | G63: Production released EASA Form 1 for (189W0001-11). AWAITS provided EO, supported w FAA Form 8110-3, as an acceptance of (AIPC not effective) tip instl and rework instr for repair completed per EO 25-777-55-190 IR dated 14.07.25. Rplcmnt Elevator (01/07) and HS Tip (22/07) installed on a/c. Job is done. 1. Hor Stab Structure initial inspections (-01C): EO 0235-2025 issued. Done by Prod. 2. Hor Stab Structure additional inspections (as per Boeing -05B): EO 0239-2025 issued. Done by Prod. 3. LH Elevator (183W0061-17; HDH0576) w FAA 8130 delivered: EO 0258-2025 (Elevator Instl) issued. Done by Prod. No FAA needed (Boeing reply) 4.a. Hor Stab Tip Replacement Option 1 - to procure new/serviseable p/n 189W0001-21 or 189W0001-23 on AOG basis. Not in market 4.b. Hor Stab Tip Replacement Option 2 - w Boeing evaluating p/n 189W0001-11 adaptation (robbed from C5-ECA). Interchangeability approval and repair for miss aligned holes (4 ea). Rejected by Boeing (July 11) due to AD/SB aspects 5. Available p/n 189W0001-11 Tip EO 0250-2025 issued (Shop inspection). Done by Prod. 6. 189W0001-21 Tip has been ordered from SOURCEOne (Sreejith). As per SOURCEONE: they have only Tip 189W0001-11 to be upgraded up to 189W0001-21 Tip. This option Rejected. 7. Alternatively. Part 21 (AWATS) was approached and provide a preliminary acceptance (Sun 13/07/2025 11:26 PM). Contact them via Teams. EO and FAA8110-3 done. (BCS ET1-GHD-25-0001) # Dmitry | H63: WITH PRODUCTION | I63: CLOSED | J63: =IF(K63="","",HYPERLINK(K63, "Link")) -> Link | K63: T:\3. Departmental Folders\10 Technical Services\ENGINEERING\Engineering Enquiry Forms\2025 EEF PDF FORMAT (SCAN)\EEF 2025-0566 C5-ECT-1/ | L63: 38 | M63: NO | N63: ECT AVIATION SUPPORT LLC | O63: GAES PROCEDURE | P63: =IF((VLOOKUP(B63,'Work Card Inquiry'!A:E,5,FALSE))="NONROUTINE",VLOOKUP(B63,'Work Card Inquiry'!A:E,2,FALSE), B63) -> 20872-0002 | Q63: 45797 | R63: DMITRY | S63: A: 23-May-2025 | T63: B: 25-May-2025 | U63: ET1-GHD-25-0001 | V63: 0235-2025, 0239-2025 | W63: OUT | X63: AMARNATH | Y63: CLOSED | AA63: ANSWERED | AB63: CLOSED
A64: 2025-0565 | B64: 20823-0045 | C64: B747-400 | D64: 27 | E64: CN-RGA-3 | F64: CRACK ON HINGE FITTING LOWER STRAP | G64: SMAL Approval received to fabricate the replacement doubler. | H64: WITH PRODUCTION | I64: CLOSED | J64: =IF(K64="","",HYPERLINK(K64, "Link")) -> Link | K64: T:\3. Departmental Folders\10 Technical Services\ENGINEERING\Engineering Enquiry Forms\2025 EEF PDF FORMAT (SCAN)\EEF 2025-0565 CN-RGA-3/ | L64: 7 | M64: YES | N64: ROYAL AIR MAROC | O64: 57-906-01 | P64: =IF((VLOOKUP(B64,'Work Card Inquiry'!A:E,5,FALSE))="NONROUTINE",VLOOKUP(B64,'Work Card Inquiry'!A:E,2,FALSE), B64) -> 20808-0282 | Q64: 45797 | R64: AMARNATH | S64: A: 5/20/2025 C: 09-Jun-2025 | T64: D: 13-Jun-2025 | U64: SR# 271139133 | W64: OUT | X64: CHANDU | AA64: ANSWERED
A65: 2025-0564 | B65: 20667-0934 | C65: B747-400F | D65: 28 | E65: TF-AMU-17 | F65: PRESSURE CHECK TOOL FABRICATION AS PER AMM 28-11-4-404-003 | G65: Answered | H65: WITH PRODUCTION | I65: CLOSED | J65: =IF(K65="","",HYPERLINK(K65, "Link")) -> Link | K65: T:\3. Departmental Folders\10 Technical Services\ENGINEERING\Engineering Enquiry Forms\2025 EEF PDF FORMAT (SCAN)\EEF 2025-0564 TF-AMU-17/ | L65: 4 | M65: YES | N65: AIR ATLANTA ICELANDIC | O65: MPD-57-480-00-01 | P65: =IF((VLOOKUP(B65,'Work Card Inquiry'!A:E,5,FALSE))="NONROUTINE",VLOOKUP(B65,'Work Card Inquiry'!A:E,2,FALSE), B65) -> 20664-1346 | Q65: 45797 | R65: JEEWANA | S65: A: 5/20/2025 | T65: B: 5/21/2025 | U65: Nil | W65: OUT | AA65: ANSWERED
A66: 2025-0563 | B66: 20667-0810 | C66: B747-400F | D66: 52 | E66: TF-AMU-17 | F66: FWD /AFT CARGO DOOR REMOVAL & INSTALLATION TOOL NOT AVAILABLE | G66: Answered | H66: WITH PRODUCTION | I66: CLOSED | J66: =IF(K66="","",HYPERLINK(K66, "Link")) -> Link | K66: T:\3. Departmental Folders\10 Technical Services\ENGINEERING\Engineering Enquiry Forms\2025 EEF PDF FORMAT (SCAN)\EEF 2025-0563 TF-AMU-17/ | L66: 6 | M66: YES | N66: AIR ATLANTA ICELANDIC | O66: MPD-52-034-03-01 | P66: =IF((VLOOKUP(B66,'Work Card Inquiry'!A:E,5,FALSE))="NONROUTINE",VLOOKUP(B66,'Work Card Inquiry'!A:E,2,FALSE), B66) -> 20664-0607 | Q66: 45797 | R66: JEEWANA | S66: A: 5/20/2025 | T66: B: 5/21/2025 | U66: Nil | W66: OUT | AA66: WIP
A67: 2025-0562 | B67: 20823-0014 | C67: B747-400 | D67: 54 | E67: CN-RGA-3 | F67: ENG#3 INLET COWL- ACOUSTIC PANEL AFT RING - CORROSION | G67: Answered | H67: WITH PRODUCTION | I67: CLOSED | J67: =IF(K67="","",HYPERLINK(K67, "Link")) -> Link | K67: T:\3. Departmental Folders\10 Technical Services\ENGINEERING\Engineering Enquiry Forms\2025 EEF PDF FORMAT (SCAN)\EEF 2025-0562 CN-RGA-3/ | L67: 3 | M67: YES | N67: ROYAL AIR MAROC | O67: 71-804-01-03 | P67: =IF((VLOOKUP(B67,'Work Card Inquiry'!A:E,5,FALSE))="NONROUTINE",VLOOKUP(B67,'Work Card Inquiry'!A:E,2,FALSE), B67) -> 20808-0300 | Q67: 45797 | R67: SUBHASH | T67: 45798 | W67: OUT | AA67: ANSWERED
A68: 2025-0561 | B68: 20862-0404 | C68: A320 | D68: 72 | E68: CN-NMQ-1 | F68: ENG#2 LPT FRAME FLAGE ASSY - BOLT SHEARED | G68: Answered | H68: WITH PRODUCTION | I68: CLOSED | J68: =IF(K68="","",HYPERLINK(K68, "Link")) -> Link | K68: T:\3. Departmental Folders\10 Technical Services\ENGINEERING\Engineering Enquiry Forms\2025 EEF PDF FORMAT (SCAN)\EEF 2025-0561 CN-NMQ-1/ | L68: 4 | M68: YES | N68: AIR ARABIA MAROC S.A. | O68: 4003600 | P68: =IF((VLOOKUP(B68,'Work Card Inquiry'!A:E,5,FALSE))="NONROUTINE",VLOOKUP(B68,'Work Card Inquiry'!A:E,2,FALSE), B68) -> 20862-0404 | Q68: 45797 | R68: SUBHASH | T68: 45798 | W68: WITHIN | AA68: ANSWERED
A69: 2025-0560 | B69: 20823-0292 | C69: B747-400 | D69: 55 | E69: CN-RGA-3 | F69: RH HORIZONTAL STABILIZER FAIRING #341 AR FOUND RIB AND CLIP CRACKED | H69: WITH PRODUCTION | I69: CLOSED | J69: =IF(K69="","",HYPERLINK(K69, "Link")) -> Link | K69: T:\3. Departmental Folders\10 Technical Services\ENGINEERING\Engineering Enquiry Forms\2025 EEF PDF FORMAT (SCAN)\EEF 2025-0560 CN-RGA-3/ | L69: 4 | M69: YES | N69: ROYAL AIR MAROC | O69: 744-SL-55-012 | P69: =IF((VLOOKUP(B69,'Work Card Inquiry'!A:E,5,FALSE))="NONROUTINE",VLOOKUP(B69,'Work Card Inquiry'!A:E,2,FALSE), B69) -> 20819-0004 | Q69: 45796 | R69: AMARNATH | W69: WITHIN | AA69: ANSWERED
A70: 2025-0559 | B70: 20823-0244 | C70: B747-400 | D70: 53 | E70: CN-RGA-3 | F70: LH FUSELAGE SKIN INNER SURFACE B/W STA 880 & 900 AND B/W STGR 23 & 24 (ILLUMINATION LIGHT CUTOUT) - CORROSION | G70: Doubler Repair performed. (BCS RAM-MRC-25-0004) # Jeewana ETS 20:00 UAE time | H70: WITH PRODUCTION | I70: CLOSED | J70: =IF(K70="","",HYPERLINK(K70, "Link")) -> Link | K70: T:\3. Departmental Folders\10 Technical Services\ENGINEERING\Engineering Enquiry Forms\2025 EEF PDF FORMAT (SCAN)\EEF 2025-0559 CN-RGA-3/ | L70: 8 | M70: YES | N70: ROYAL AIR MAROC | O70: 53-880-01 | P70: =IF((VLOOKUP(B70,'Work Card Inquiry'!A:E,5,FALSE))="NONROUTINE",VLOOKUP(B70,'Work Card Inquiry'!A:E,2,FALSE), B70) -> 20810-0101 | Q70: 45796 | R70: JEEWANA | S70: A: 5/19/2025 | T70: B: 5/27/2025 C: 6/9/2025 | U70: RAM-MRC-25-0004 | W70: OUT | AA70: ANSWERED
A71: 2025-0558 | B71: 20865-0064 | C71: A320 | D71: 57 | E71: CN-NMQ-1 | F71: LH WING LE INBD SLAT TOP SKIN NOSE AREA RIB 2 AND RIB 3 - DENT - EXISTING ADJ REPAIR EXTENSION | G71: (Dossier# 81595201/010) # Chandu 4. w Production, RDAF received and issued. 3. w Production, To disaccemble the existing repair and extending the cutout and installing the repair pre Airbus Dossier. 2. w OEM, Damage report & Repair prosal to extend the existing adj repair. 1.w Production, Priliminary inspection instructions to ensure thedented surface is crack free. | H71: WITH PRODUCTION | I71: CLOSED | J71: =IF(K71="","",HYPERLINK(K71, "Link")) -> Link | K71: T:\3. Departmental Folders\10 Technical Services\ENGINEERING\Engineering Enquiry Forms\2025 EEF PDF FORMAT (SCAN)\EEF 2025-0558 CN-NMQ-1/ | L71: 6 | M71: YES | N71: AIR ARABIA MAROC S.A. | O71: ZL-500-02-1L | P71: =IF((VLOOKUP(B71,'Work Card Inquiry'!A:E,5,FALSE))="NONROUTINE",VLOOKUP(B71,'Work Card Inquiry'!A:E,2,FALSE), B71) -> 20862-0042 | Q71: 45796 | R71: CHANDU | S71: A: 19-May-2025 | U71: 81595201 | W71: OUT | AA71: ANSWERED
A72: 2025-0557 | B72: 20865-0072 | C72: A320 | D72: 49 | E72: CN-NMQ-1 | F72: APU AIR INTAKE - STRUCTURE OF THE AIR INLET DUCT - DELAMINATION ON THE SANDWICH | G72: ANSWERED | H72: WITH PRODUCTION | I72: CLOSED | J72: =IF(K72="","",HYPERLINK(K72, "Link")) -> Link | K72: T:\3. Departmental Folders\10 Technical Services\ENGINEERING\Engineering Enquiry Forms\2025 EEF PDF FORMAT (SCAN)\EEF 2025-0557 CN-NMQ-1/ | L72: 6 | M72: YES | N72: AIR ARABIA MAROC S.A. | O72: 491600-B1-1 | P72: =IF((VLOOKUP(B72,'Work Card Inquiry'!A:E,5,FALSE))="NONROUTINE",VLOOKUP(B72,'Work Card Inquiry'!A:E,2,FALSE), B72) -> 20862-0314 | Q72: 45796 | R72: SUBHASH | S72: 5/19/2025 C: 20-May-2025 | T72: 45800 | W72: OUT | AA72: ANSWERED
A73: 2025-0556 | B73: 20823-0180 | C73: B747-400 | D73: 53 | E73: CN-RGA-3 | F73: LH LOWER FAIRING SUPPORT FRAME CORROSION AT STA 1480 | G73: Repaired by trimming the damaged area and adding the additonal reinforcement per (BCS RAM-MRC-25-0017) # Chandu | H73: WITH PRODUCTION | I73: CLOSED | J73: =IF(K73="","",HYPERLINK(K73, "Link")) -> Link | K73: T:\3. Departmental Folders\10 Technical Services\ENGINEERING\Engineering Enquiry Forms\2025 EEF PDF FORMAT (SCAN)\EEF 2025-0556 CN-RGA-3/ | L73: 10 | M73: YES | N73: ROYAL AIR MAROC | O73: 53-868-01 | P73: =IF((VLOOKUP(B73,'Work Card Inquiry'!A:E,5,FALSE))="NONROUTINE",VLOOKUP(B73,'Work Card Inquiry'!A:E,2,FALSE), B73) -> 20809-0272 | Q73: 45796 | R73: AMARNATH | S73: C: 11-Jun-2025 | T73: D: 11-Jun-2025 | U73: RAM-MRC-25-0017 | W73: OUT | X73: CHANDU | AA73: WIP
A74: 2025-0555 | B74: 20823-0023 | C74: B747-400 | D74: 54 | E74: CN-RGA-3 | F74: ENG#1 INBD FAN COWL LOWER BONDED DOUBLER - CHAPPING | G74: ANSWERED | H74: WITH PRODUCTION | I74: CLOSED | J74: =IF(K74="","",HYPERLINK(K74, "Link")) -> Link | K74: T:\3. Departmental Folders\10 Technical Services\ENGINEERING\Engineering Enquiry Forms\2025 EEF PDF FORMAT (SCAN)\EEF 2025-0555 CN-RGA-3/ | L74: 4 | M74: YES | N74: ROYAL AIR MAROC | O74: 71-808-01-01 | P74: =IF((VLOOKUP(B74,'Work Card Inquiry'!A:E,5,FALSE))="NONROUTINE",VLOOKUP(B74,'Work Card Inquiry'!A:E,2,FALSE), B74) -> 20808-0302 | Q74: 45795 | R74: SUBHASH | S74: 45795 | T74: 45796 | U74: NIL | W74: OUT | AA74: ANSWERED
A75: 2025-0554 | B75: 20823-0041 | C75: B747-400 | D75: 28 | E75: CN-RGA-3 | F75: P/N & INSTALATION PROCEDURE FOR REFUELING RECEPTACALE CAP & LANYARD | G75: ANSWERED | H75: WITH PRODUCTION | I75: CLOSED | J75: =IF(K75="","",HYPERLINK(K75, "Link")) -> Link | K75: T:\3. Departmental Folders\10 Technical Services\ENGINEERING\Engineering Enquiry Forms\2025 EEF PDF FORMAT (SCAN)\EEF 2025-0554 CN-RGA-3/ | L75: 4 | M75: YES | N75: ROYAL AIR MAROC | O75: AF-28-13 | P75: =IF((VLOOKUP(B75,'Work Card Inquiry'!A:E,5,FALSE))="NONROUTINE",VLOOKUP(B75,'Work Card Inquiry'!A:E,2,FALSE), B75) -> 20815-0089 | Q75: 45793 | R75: JEEWANA | S75: A: 5/16/2025 B: 5/18/2025 | U75: NIL | W75: TBD | AA75: WIP
A76: 2025-0553 | B76: 20823-0176 | C76: B747-400 | D76: 53 | E76: CN-RGA-3 | F76: MAIN DECK SEAT TRACK LBL 98.58, STA 660 AND STA 670 - DAMAGE - ALT SURFACE COATING | G76: (BCS# RAM-MRC-25-0003) #Chandu 2. w Production, RDR Received & Issued. 1. w Production, to repair as per SRM 53-00-52 R6 but with surface finish of CCC in lue of Anodization per BCS. | H76: WITH PRODUCTION | I76: CLOSED | J76: =IF(K76="","",HYPERLINK(K76, "Link")) -> Link | K76: T:\3. Departmental Folders\10 Technical Services\ENGINEERING\Engineering Enquiry Forms\2025 EEF PDF FORMAT (SCAN)\EEF 2025-0553 CN-RGA-3/ | L76: 7 | M76: YES | N76: ROYAL AIR MAROC | O76: 25-025-04 | P76: =IF((VLOOKUP(B76,'Work Card Inquiry'!A:E,5,FALSE))="NONROUTINE",VLOOKUP(B76,'Work Card Inquiry'!A:E,2,FALSE), B76) -> 20810-0046 | Q76: 45792 | R76: CHANDU | S76: A: 15-May-2025 C: 02-Jun-2025 | T76: B: 21-May-2025 D: 12-Jun-2025 | U76: RAM-MRC-25-0003 | W76: OUT | AA76: ANSWERED
A77: 2025-0552 | B77: 20823-0060 | C77: B747-400 | D77: 54 | E77: CN-RGA-3 | F77: RH WING LOWER PANEL RIB WBL 132.45 (65B11512-18) - CORROSION | G77: Repair Accomplished, RDR Received and issued to production. # Chandu | H77: WITH PRODUCTION | I77: CLOSED | J77: =IF(K77="","",HYPERLINK(K77, "Link")) -> Link | K77: T:\3. Departmental Folders\10 Technical Services\ENGINEERING\Engineering Enquiry Forms\2025 EEF PDF FORMAT (SCAN)\EEF 2025-0552 CN-RGA-3/ | L77: 10 | M77: YES | N77: ROYAL AIR MAROC | O77: 32-820-01 | P77: =IF((VLOOKUP(B77,'Work Card Inquiry'!A:E,5,FALSE))="NONROUTINE",VLOOKUP(B77,'Work Card Inquiry'!A:E,2,FALSE), B77) -> 20808-0119 | Q77: 45792 | R77: AMARNATH | S77: A: 15-May-2025 C: 20-May-2025 F: 28-May-2025 I: 26-Jun-2025 | T77: B: 15-May-2025 D: 21-May-2025 E: 27-May-2025 G: 05-Jun-2025 H: 12-Jun-2025 J: 29-Jun-2025 | U77: RAM-MRC-25-0010 | W77: OUT | X77: CHANDU | AA77: ANSWERED
A78: 2025-0551 | B78: 20823-0108 | C78: B747-400 | D78: 57 | E78: CN-RGA-3 | F78: LH T/E WS 400 RIB ASSY LOWER CHORD CORROSION | G78: Part Replacement. Part ordered. | H78: WITH PRODUCTION | I78: CLOSED | J78: =IF(K78="","",HYPERLINK(K78, "Link")) -> Link | K78: T:\3. Departmental Folders\10 Technical Services\ENGINEERING\Engineering Enquiry Forms\2025 EEF PDF FORMAT (SCAN)\EEF 2025-0551 CN-RGA-3/ | L78: 4 | M78: YES | N78: ROYAL AIR MAROC | O78: 57-856-01 | P78: =IF((VLOOKUP(B78,'Work Card Inquiry'!A:E,5,FALSE))="NONROUTINE",VLOOKUP(B78,'Work Card Inquiry'!A:E,2,FALSE), B78) -> 20808-0274 | Q78: 45791 | R78: JEEWANA | U78: NIL | W78: OUT | X78: AMARNATH | AA78: ANSWERED
A79: 2025-0550 | B79: 20823-0188 | C79: B747-400 | D79: 27 | E79: CN-RGA-3 | F79: FLAP TRACK #2 FWD FITTING BEARING - MIGRATED - REPLACEMENT | G79: (SB 747-57-2325) #Chandu 2. w Production, Due to unavailability of the certain tools, EO issued per SB to remove the complete fitting and sent to Machine shop to perform Bering replacement. 1. w Production, Bearing Replacement instruction EO issued IAW SB 57-2325. | H79: WITH PRODUCTION | I79: CLOSED | J79: =IF(K79="","",HYPERLINK(K79, "Link")) -> Link | K79: T:\3. Departmental Folders\10 Technical Services\ENGINEERING\Engineering Enquiry Forms\2025 EEF PDF FORMAT (SCAN)\EEF 2025-0550 CN-RGA-3/ | L79: 6 | M79: YES | N79: ROYAL AIR MAROC | O79: 57-620-00-02 | P79: =IF((VLOOKUP(B79,'Work Card Inquiry'!A:E,5,FALSE))="NONROUTINE",VLOOKUP(B79,'Work Card Inquiry'!A:E,2,FALSE), B79) -> 20808-0261 | Q79: 45791 | R79: CHANDU | S79: A: 15-May-2025 C: 21-May-2025 | T79: B: 16-May-2025 D: 22-May-2025 | U79: SB 57-2325 | V79: EO 0229-2025 Rev. 00 | W79: WITHIN | AA79: ANSWERED
A80: 2025-0549 | B80: 20744-0750 | C80: A319-115 | D80: 53 | E80: A6-CJE-1 | F80: AIR STAIRS REMOVAL/INST TOOL NOT AVAIALABLE - MULTIPLE NRC'S | G80: ANSWERED | H80: WITH PRODUCTION | I80: CLOSED | J80: =IF(K80="","",HYPERLINK(K80, "Link")) -> Link | K80: T:\3. Departmental Folders\10 Technical Services\ENGINEERING\Engineering Enquiry Forms\2025 EEF PDF FORMAT (SCAN)\EEF 2025-0549 A6-CJE-1/ | L80: 4 | M80: YES | N80: EMIRATES | O80: MPD-200129-03-1 | P80: =IF((VLOOKUP(B80,'Work Card Inquiry'!A:E,5,FALSE))="NONROUTINE",VLOOKUP(B80,'Work Card Inquiry'!A:E,2,FALSE), B80) -> 20744-0750 | Q80: 45791 | R80: SUBHASH | T80: B 27-MAY-2025 | U80: 81582864 | W80: OUT | AA80: ANSWERED
A81: 2025-0548 | B81: 20667-0658 | C81: B747-400F | D81: 54 | E81: TF-AMU-17 | F81: ENG# 3 NOSE COWL ACOUSTIC PANEL AT 6 O'CLOCK - DENTS - ADHESIVE REPAIR | G81: #Chandu 1. w Production, Fabrication Form & Inspection Check list issued to perform repair per SRM 54-15-01 R3. | H81: WITH PRODUCTION | I81: CLOSED | J81: =IF(K81="","",HYPERLINK(K81, "Link")) -> Link | K81: T:\3. Departmental Folders\10 Technical Services\ENGINEERING\Engineering Enquiry Forms\2025 EEF PDF FORMAT (SCAN)\EEF 2025-0548 TF-AMU-17/ | L81: 1 | M81: NO | N81: AIR ATLANTA ICELANDIC | O81: MPD-71-804-01-03 | P81: =IF((VLOOKUP(B81,'Work Card Inquiry'!A:E,5,FALSE))="NONROUTINE",VLOOKUP(B81,'Work Card Inquiry'!A:E,2,FALSE), B81) -> 20664-1490 | Q81: 45790 | R81: CHANDU | T81: B: 14-May-2025 | U81: NIL | W81: WITHIN | AA81: ANSWERED
A82: 2025-0547 | B82: 20823-0158 | C82: B747-400 | D82: 78 | E82: CN-RGA-3 | F82: ENG#3 OTBD THRUST REVERSER - UPPER BIFURICATION PANEL- CORROSSION | G82: ANSWERED | H82: WITH PRODUCTION | I82: CLOSED | J82: =IF(K82="","",HYPERLINK(K82, "Link")) -> Link | K82: T:\3. Departmental Folders\10 Technical Services\ENGINEERING\Engineering Enquiry Forms\2025 EEF PDF FORMAT (SCAN)\EEF 2025-0547 CN-RGA-3/ | L82: 8 | M82: YES | N82: ROYAL AIR MAROC | O82: 71-812-01-03 | P82: =IF((VLOOKUP(B82,'Work Card Inquiry'!A:E,5,FALSE))="NONROUTINE",VLOOKUP(B82,'Work Card Inquiry'!A:E,2,FALSE), B82) -> 20808-0312 | Q82: 45790 | R82: SUBHASH | S82: 45797 | U82: NIL | W82: OUT | AA82: ANSWERED
A83: 2025-0546 | B83: 20823-0035 | C83: B747-400 | D83: 78 | E83: CN-RGA-3 | F83: ENG#2 AFT THRUST REVERSER AFT EDGE - CORROSION | G83: ANSWERED | H83: WITH PRODUCTION | I83: CLOSED | J83: =IF(K83="","",HYPERLINK(K83, "Link")) -> Link | K83: T:\3. Departmental Folders\10 Technical Services\ENGINEERING\Engineering Enquiry Forms\2025 EEF PDF FORMAT (SCAN)\EEF 2025-0546 CN-RGA-3/ | L83: 10 | M83: YES | N83: ROYAL AIR MAROC | O83: 71-812-01-02 | P83: =IF((VLOOKUP(B83,'Work Card Inquiry'!A:E,5,FALSE))="NONROUTINE",VLOOKUP(B83,'Work Card Inquiry'!A:E,2,FALSE), B83) -> 20808-0311 | Q83: 45790 | R83: SUBHASH | S83: 45796 | U83: NIL | W83: OUT | AA83: ANSWERED
A84: 2025-0545 | B84: 20823-0072 | C84: B747-400 | D84: 57 | E84: CN-RGA-3 | F84: RH WING LOWER PANEL SUPPORT BEAM (65B12272-22) - CORROSION | G84: Alternative Extrusion, CCC in leiu CAA. Not an primary structure Beam already formed, HT Done, Installation in progress, Awaiting production response. RDR received fom Boeing (BCS RAM-MRC-25-0009) # Subhash | H84: WITH PRODUCTION | I84: CLOSED | J84: =IF(K84="","",HYPERLINK(K84, "Link")) -> Link | K84: T:\3. Departmental Folders\10 Technical Services\ENGINEERING\Engineering Enquiry Forms\2025 EEF PDF FORMAT (SCAN)\EEF 2025-0545 CN-RGA-3/ | L84: 10 | M84: YES | N84: ROYAL AIR MAROC | O84: 57-896-01 | P84: =IF((VLOOKUP(B84,'Work Card Inquiry'!A:E,5,FALSE))="NONROUTINE",VLOOKUP(B84,'Work Card Inquiry'!A:E,2,FALSE), B84) -> 20808-0280 | Q84: 45790 | R84: AMARNATH | T84: J: 10-Jul-2025 | U84: RAM-MRC-25-0009 | W84: OUT | X84: SUBHASH | AA84: ANSWERED
A85: 2025-0544 | B85: 20823-0063 | C85: B747-400 | D85: 54 | E85: CN-RGA-3 | F85: ENG#4 INLET COWL ACOUSTIC PANEL CORROSION | G85: Answered | H85: WITH PRODUCTION | I85: CLOSED | J85: =IF(K85="","",HYPERLINK(K85, "Link")) -> Link | K85: T:\3. Departmental Folders\10 Technical Services\ENGINEERING\Engineering Enquiry Forms\2025 EEF PDF FORMAT (SCAN)\EEF 2025-0544 CN-RGA-3/ | L85: 6 | M85: YES | N85: ROYAL AIR MAROC | O85: 71-804-01-04 | P85: =IF((VLOOKUP(B85,'Work Card Inquiry'!A:E,5,FALSE))="NONROUTINE",VLOOKUP(B85,'Work Card Inquiry'!A:E,2,FALSE), B85) -> 20808-0301 | Q85: 45789 | R85: SUBHASH | T85: 45799 | W85: OUT | AA85: ANSWERED
A86: 2025-0543 | B86: 20831-0086 | C86: A320-200 | D86: 34 | E86: AP-BOQ | F86: INSTALLATION STEP FOR T/TISS (1000SG) ON 82VU NOT EXIST IN TASK CARD 12-21-13-100-001-A | G86: Answered | H86: WITH PRODUCTION | I86: CLOSED | J86: =IF(K86="","",HYPERLINK(K86, "Link")) -> Link | K86: T:\3. Departmental Folders\10 Technical Services\ENGINEERING\Engineering Enquiry Forms\2025 EEF PDF FORMAT (SCAN)\EEF 2025-0543 AP-BOQ-1/ | L86: 3 | M86: YES | N86: FLY JINNAH SERVICES (PVT) LIMITED | O86: 122113-AA-1 | P86: =IF((VLOOKUP(B86,'Work Card Inquiry'!A:E,5,FALSE))="NONROUTINE",VLOOKUP(B86,'Work Card Inquiry'!A:E,2,FALSE), B86) -> 20831-0086 | Q86: 45788 | R86: JEEWANA | T86: B: 5/11/2025 | U86: Dossier: 81589935_001 | W86: WITHIN | AA86: ANSWERED
A87: 2025-0542 | B87: 20839-0010 | C87: A320-200 | D87: 11 | E87: AP-BOQ | F87: FIRST OFFICER OXYGENMASK DECAL - P/N NOT IN IPC | G87: Answered | H87: WITH PRODUCTION | I87: CLOSED | J87: =IF(K87="","",HYPERLINK(K87, "Link")) -> Link | K87: T:\3. Departmental Folders\10 Technical Services\ENGINEERING\Engineering Enquiry Forms\2025 EEF PDF FORMAT (SCAN)\EEF 2025-0542 AP-BOQ-1/ | L87: 3 | M87: YES | N87: FLY JINNAH SERVICES (PVT) LIMITED | O87: CWR-004-6 | P87: =IF((VLOOKUP(B87,'Work Card Inquiry'!A:E,5,FALSE))="NONROUTINE",VLOOKUP(B87,'Work Card Inquiry'!A:E,2,FALSE), B87) -> 20839-0010 | Q87: 45784 | R87: SUBHASH | T87: B: 11-May-2025 | W87: WITHIN | AA87: ANSWERED
A88: 2025-0541 | B88: 20747-0190 | C88: A319-115 | D88: 53 | E88: A6-CJE-1 | F88: SEAT TRACK FR 24-35 - CORROSION - SPLICE REPAIR Fabrication form Request | G88: #Chandu 1. w Production, Fabrication Form & Inspection Check list issued to perform repair per SRM 53-21-15-300-003 & 008. | H88: WITH PRODUCTION | I88: CLOSED | J88: =IF(K88="","",HYPERLINK(K88, "Link")) -> Link | K88: T:\3. Departmental Folders\10 Technical Services\ENGINEERING\Engineering Enquiry Forms\2025 EEF PDF FORMAT (SCAN)\EEF 2025-0541 A6-CJE-1/ | L88: 1 | M88: NO | N88: EMIRATES | O88: MPD-SEWCMPD-25-0019 | P88: =IF((VLOOKUP(B88,'Work Card Inquiry'!A:E,5,FALSE))="NONROUTINE",VLOOKUP(B88,'Work Card Inquiry'!A:E,2,FALSE), B88) -> 20760-0019 | Q88: 45782 | R88: CHANDU | W88: WITHIN | AA88: ANSWERED
A89: 2025-0540 | B89: 20834-0053 | C89: A320-200 | D89: 23 | E89: AP-BOQ | F89: HF FEEDER FLANGE UNDER DORSAL FIN P./N IDENTIFICATION | G89: Answered | H89: WITH PRODUCTION | I89: CLOSED | J89: =IF(K89="","",HYPERLINK(K89, "Link")) -> Link | K89: T:\3. Departmental Folders\10 Technical Services\ENGINEERING\Engineering Enquiry Forms\2025 EEF PDF FORMAT (SCAN)\EEF 2025-0540 AP-BOQ-1/ | L89: 3 | M89: YES | N89: FLY JINNAH SERVICES (PVT) LIMITED | O89: ZL-300-02-1 | P89: =IF((VLOOKUP(B89,'Work Card Inquiry'!A:E,5,FALSE))="NONROUTINE",VLOOKUP(B89,'Work Card Inquiry'!A:E,2,FALSE), B89) -> 20831-0035 | Q89: 45778 | R89: JEEWANA | T89: B: 5/2/2025 | W89: TBD | AA89: WIP
A90: 2025-0539 | B90: 20834-0072 | C90: A320-200 | D90: 55 | E90: AP-BOQ | F90: HYD LINE ATTACH BRACKAET - CORRRODED NEAR RUDDER ACTUATOR FITTING | G90: Answered | H90: WITH PRODUCTION | I90: CLOSED | J90: =IF(K90="","",HYPERLINK(K90, "Link")) -> Link | K90: T:\3. Departmental Folders\10 Technical Services\ENGINEERING\Engineering Enquiry Forms\2025 EEF PDF FORMAT (SCAN)\EEF 2025-0539 AP-BOQ-1/ | L90: 2 | M90: YES | N90: FLY JINNAH SERVICES (PVT) LIMITED | O90: 553600-01-1 | P90: =IF((VLOOKUP(B90,'Work Card Inquiry'!A:E,5,FALSE))="NONROUTINE",VLOOKUP(B90,'Work Card Inquiry'!A:E,2,FALSE), B90) -> 20831-0447 | Q90: 45778 | R90: SUBHASH | T90: B: 08-May-2025 C: 08-May-2025 D: 11-May-2025 | W90: TBD | AA90: ANSWERED
A91: 2025-0538 | B91: 20834-0044 | C91: A320-200 | D91: 49 | E91: AP-BOQ | F91: APU EXHAUST MUFFLER - CRACK | G91: Answered | H91: WITH PRODUCTION | I91: CLOSED | J91: =IF(K91="","",HYPERLINK(K91, "Link")) -> Link | K91: T:\3. Departmental Folders\10 Technical Services\ENGINEERING\Engineering Enquiry Forms\2025 EEF PDF FORMAT (SCAN)\EEF 2025-0538 AP-BOQ-1/ | L91: 3 | M91: YES | N91: FLY JINNAH SERVICES (PVT) LIMITED | O91: ZL-317-01-1 | P91: =IF((VLOOKUP(B91,'Work Card Inquiry'!A:E,5,FALSE))="NONROUTINE",VLOOKUP(B91,'Work Card Inquiry'!A:E,2,FALSE), B91) -> 20831-0037 | Q91: 45777 | R91: SUBHASH | T91: B: 01-May-2025 | W91: WITHIN | X91: JEEWANA | AA91: ANSWERED
A92: 2025-0537 | B92: 20834-0063 | C92: A320-200 | D92: 57 | E92: AP-BOQ | F92: CORROSION AT LH WING REAR SPAR MLG SUPPORT FITTING BETWEEN RIB 5- RIB 8 | G92: ANSWERED | H92: WITH PRODUCTION | I92: CLOSED | J92: =IF(K92="","",HYPERLINK(K92, "Link")) -> Link | K92: T:\3. Departmental Folders\10 Technical Services\ENGINEERING\Engineering Enquiry Forms\2025 EEF PDF FORMAT (SCAN)\EEF 2025-0537 AP-BOQ-1/ | L92: 4 | M92: YES | N92: FLY JINNAH SERVICES (PVT) LIMITED | O92: 575151-03-1L | P92: =IF((VLOOKUP(B92,'Work Card Inquiry'!A:E,5,FALSE))="NONROUTINE",VLOOKUP(B92,'Work Card Inquiry'!A:E,2,FALSE), B92) -> 20831-0542 | Q92: 45777 | R92: AMARNATH | T92: B: 4/29/2025 D: 5/09/2025 F: 5/12/2025 | U92: Dossier 81588046 | W92: OUT | AA92: ANSWERED
A93: 2025-0536 | B93: 20834-0045 | C93: A320-200 | D93: 57 | E93: AP-BOQ | F93: CORROSION AT RH WING REAR SPAR MLG SUPPORT FITTING BETWEEN RIB 5- RIB 8 | G93: ANSWERED | H93: WITH PRODUCTION | I93: CLOSED | J93: =IF(K93="","",HYPERLINK(K93, "Link")) -> Link | K93: T:\3. Departmental Folders\10 Technical Services\ENGINEERING\Engineering Enquiry Forms\2025 EEF PDF FORMAT (SCAN)\EEF 2025-0536 AP-BOQ-1/ | L93: 4 | M93: YES | N93: FLY JINNAH SERVICES (PVT) LIMITED | O93: 575151-03-1R | P93: =IF((VLOOKUP(B93,'Work Card Inquiry'!A:E,5,FALSE))="NONROUTINE",VLOOKUP(B93,'Work Card Inquiry'!A:E,2,FALSE), B93) -> 20831-0539 | Q93: 45776 | R93: AMARNATH | T93: B: 4/29/2025 D: 5/09/2025 F: 5/12/2025 | U93: DOssier 81588050 | W93: OUT | AA93: ANSWERED
A94: 2025-0535 | B94: 20744-0300 | C94: A319-115 | E94: A6-CJE-1 | F94: AIR STAIRS - REMOVAL/INST TOOL NOT AVAIALABLE | G94: Answered | H94: WITH PRODUCTION | I94: CLOSED | J94: =IF(K94="","",HYPERLINK(K94, "Link")) -> Link | K94: T:\3. Departmental Folders\10 Technical Services\ENGINEERING\Engineering Enquiry Forms\2025 EEF PDF FORMAT (SCAN)\EEF 2025-0535 A6-CJE-1/ | L94: 5 | M94: YES | N94: EMIRATES | O94: MPD-531181-01-1 | P94: =IF((VLOOKUP(B94,'Work Card Inquiry'!A:E,5,FALSE))="NONROUTINE",VLOOKUP(B94,'Work Card Inquiry'!A:E,2,FALSE), B94) -> 20744-0300 | Q94: 45771 | R94: SUBHASH | T94: B: 11-May-2025 | U94: Airbus TR 81582864 | W94: WITHIN | AA94: ANSWERED
A95: 2025-0534 | B95: 20747-0265 | C95: A319-115 | D95: 73 | E95: A6-CJE-1 | F95: ENG #1 BONDING JUMPER - P/N IDENTIFICATION | G95: Answered | H95: WITH PRODUCTION | I95: CLOSED | J95: =IF(K95="","",HYPERLINK(K95, "Link")) -> Link | K95: T:\3. Departmental Folders\10 Technical Services\ENGINEERING\Engineering Enquiry Forms\2025 EEF PDF FORMAT (SCAN)\EEF 2025-0534 A6-CJE-1/ | L95: 2 | M95: NO | N95: EMIRATES | O95: MPD-ZL-453-01-1/450 | P95: =IF((VLOOKUP(B95,'Work Card Inquiry'!A:E,5,FALSE))="NONROUTINE",VLOOKUP(B95,'Work Card Inquiry'!A:E,2,FALSE), B95) -> 20760-0050 | Q95: 45770 | R95: SUBHASH | T95: B: 24-Apr-2025 | W95: WITHIN | X95: AMARNATH | AA95: ANSWERED
A96: 2025-0533 | B96: 20744-0527/0528 | C96: A319-115 | D96: 57 | E96: A6-CJE-1 | F96: SLAT #4 ENDOSCOPE INSPECTION LH / RH | G96: Provided alternative method for inspection | H96: WITH PRODUCTION | I96: CLOSED | J96: =IF(K96="","",HYPERLINK(K96, "Link")) -> Link | K96: T:\3. Departmental Folders\10 Technical Services\ENGINEERING\Engineering Enquiry Forms\2025 EEF PDF FORMAT (SCAN)\EEF 2025-0533 A6-CJE-1/ | L96: 5 | M96: YES | N96: EMIRATES | O96: MPD-574504-02-1/500 MPD-574504-02-1/600 | P96: =IF((VLOOKUP(B96,'Work Card Inquiry'!A:E,5,FALSE))="NONROUTINE",VLOOKUP(B96,'Work Card Inquiry'!A:E,2,FALSE), B96) -> #N/A | Q96: 45770 | R96: AMARNATH | W96: OUT | AA96: ANSWERED
A97: 2025-0532 | B97: 20744-0209 / 20744-0207 | C97: A319-115 | D97: 52 | E97: A6-CJE-1 | F97: TASK CARD 319-52-10-00-05-1/842 & 319-52-10-00-05-1/832 CLARIFICATION | G97: Answered | H97: WITH PRODUCTION | I97: CLOSED | J97: =IF(K97="","",HYPERLINK(K97, "Link")) -> Link | K97: T:\3. Departmental Folders\10 Technical Services\ENGINEERING\Engineering Enquiry Forms\2025 EEF PDF FORMAT (SCAN)\EEF 2025-0532 A6-CJE-1/ | L97: 3 | M97: YES | N97: EMIRATES | O97: MPD-521000-05-1/842 MPD-521000-05-1/832 | P97: =IF((VLOOKUP(B97,'Work Card Inquiry'!A:E,5,FALSE))="NONROUTINE",VLOOKUP(B97,'Work Card Inquiry'!A:E,2,FALSE), B97) -> #N/A | Q97: 45770 | R97: JEEWANA | W97: TBD | AA97: WIP
A98: 2025-0531 | B98: 20747-0202 | C98: A319-115 | D98: 25 | E98: A6-CJE-1 | F98: AFT CABIN ATTEND SEAT LWR SUPPORT PLATE - CORRODED | G98: ANSWERED | H98: WITH PRODUCTION | I98: CLOSED | J98: =IF(K98="","",HYPERLINK(K98, "Link")) -> Link | K98: T:\3. Departmental Folders\10 Technical Services\ENGINEERING\Engineering Enquiry Forms\2025 EEF PDF FORMAT (SCAN)\EEF 2025-0531 A6-CJE-1/ | L98: 10 | M98: YES | N98: EMIRATES | O98: MPD-SEWCMPD-25-0003/200 | P98: =IF((VLOOKUP(B98,'Work Card Inquiry'!A:E,5,FALSE))="NONROUTINE",VLOOKUP(B98,'Work Card Inquiry'!A:E,2,FALSE), B98) -> 20758-0105 | Q98: 45770 | R98: SUBHASH | W98: OUT | AA98: ANSWERED
A99: 2025-0530 | B99: 20747-0180 | C99: A319-115 | D99: 25 | E99: A6-CJE-1 | F99: EXECUTIVE LOUNGE COCKTAIL TABALE BASE PLATE CORRODED | G99: Repair proposal sent to Emirates | H99: WITH PRODUCTION | I99: CLOSED | J99: =IF(K99="","",HYPERLINK(K99, "Link")) -> Link | K99: T:\3. Departmental Folders\10 Technical Services\ENGINEERING\Engineering Enquiry Forms\2025 EEF PDF FORMAT (SCAN)\EEF 2025-0530 A6-CJE-1/ | L99: 6 | M99: YES | N99: EMIRATES | O99: MPD-252100-01-2J/200 | P99: =IF((VLOOKUP(B99,'Work Card Inquiry'!A:E,5,FALSE))="NONROUTINE",VLOOKUP(B99,'Work Card Inquiry'!A:E,2,FALSE), B99) -> 20758-0103 | Q99: 45770 | R99: JEEWANA | W99: TBD | AA99: WIP
A100: 2025-0529 | B100: 20747-0203 | C100: A319-115 | D100: 25 | E100: A6-CJE-1 | F100: EXECUTIVE LOUNGE PALLET CORRODED | G100: Repair proposal sent to Emirates | H100: WITH PRODUCTION | I100: CLOSED | J100: =IF(K100="","",HYPERLINK(K100, "Link")) -> Link | K100: T:\3. Departmental Folders\10 Technical Services\ENGINEERING\Engineering Enquiry Forms\2025 EEF PDF FORMAT (SCAN)\EEF 2025-0529 A6-CJE-1/ | L100: 6 | M100: YES | N100: EMIRATES | O100: MPD-252100-01-2J/200 | P100: =IF((VLOOKUP(B100,'Work Card Inquiry'!A:E,5,FALSE))="NONROUTINE",VLOOKUP(B100,'Work Card Inquiry'!A:E,2,FALSE), B100) -> 20758-0103 | Q100: 45769 | R100: AMARNATH | W100: TBD | AA100: ANSWERED
A101: 2025-0528 | B101: 20667-0407 | C101: B747-400F | D101: 32 | E101: TF-AMU-17 | F101: ALTERNATIVE P/N CLARIFICATION | G101: ANSWERED | H101: WITH PRODUCTION | I101: CLOSED | J101: =IF(K101="","",HYPERLINK(K101, "Link")) -> Link | K101: T:\3. Departmental Folders\10 Technical Services\ENGINEERING\Engineering Enquiry Forms\2025 EEF PDF FORMAT (SCAN)\EEF 2025-0528 TF-AMU-17/ | L101: 3 | M101: YES | N101: AIR ATLANTA ICELANDIC | O101: MPD-32-014A01-02 | P101: =IF((VLOOKUP(B101,'Work Card Inquiry'!A:E,5,FALSE))="NONROUTINE",VLOOKUP(B101,'Work Card Inquiry'!A:E,2,FALSE), B101) -> 20664-0459 | Q101: 45764 | R101: JEEWANA | W101: TBD | AA101: ANSWERED
A102: 2025-0527 | B102: 20667-0689 | C102: B747-400F | D102: 54 | E102: TF-AMU-17 | F102: ENG #2 NOSE COWL DENTS - FABRICATION REQUEST | G102: ANSWEED | H102: WITH PRODUCTION | I102: CLOSED | J102: =IF(K102="","",HYPERLINK(K102, "Link")) -> Link | K102: T:\3. Departmental Folders\10 Technical Services\ENGINEERING\Engineering Enquiry Forms\2025 EEF PDF FORMAT (SCAN)\EEF 2025-0527 TF-AMU-17/ | L102: 2 | M102: NO | N102: AIR ATLANTA ICELANDIC | O102: MPD-57-956-01-01 | P102: =IF((VLOOKUP(B102,'Work Card Inquiry'!A:E,5,FALSE))="NONROUTINE",VLOOKUP(B102,'Work Card Inquiry'!A:E,2,FALSE), B102) -> 20664-1461 | Q102: 45764 | R102: SUBHASH | T102: B: 17-APR-2025 | W102: WITHIN | AA102: ANSWERED
A103: 2025-0526 | B103: 20773-0017 | C103: A320-200 | D103: 53 | E103: SU-AA1-1 | F103: P/N VERIFICATION | G103: Answered | H103: WITH PRODUCTION | I103: CLOSED | J103: =IF(K103="","",HYPERLINK(K103, "Link")) -> Link | K103: T:\3. Departmental Folders\10 Technical Services\ENGINEERING\Engineering Enquiry Forms\2025 EEF PDF FORMAT (SCAN)\EEF 2025-0526 SU-AAI-1/ | L103: 3 | M103: YES | N103: AIR ARABIA EGYPT SAE | O103: ZL-311-01-1 | P103: =IF((VLOOKUP(B103,'Work Card Inquiry'!A:E,5,FALSE))="NONROUTINE",VLOOKUP(B103,'Work Card Inquiry'!A:E,2,FALSE), B103) -> 20771-0017 | Q103: 45764 | R103: JEEWANA | T103: B: 4/18/2025 | W103: WITHIN | AA103: ANSWERED
...
